Workbook

Sheet Sales_raw_data
A1: Order ID | B1: Product ID | C1: Product Name | D1: Category | E1: Region | F1: Sales Channel | G1: Sales Rep | H1: Order Date | I1: Units Sold | J1: Unit Price (₦) | K1: Discount (%) | L1: Payment Status | M1: Total Sales (₦) | N1: Net Revenue (₦) | O1: Revenue Tier
A2: ORD-1001 | B2: PKG-001 | D2: BEVERAGES | E2: NORTH | F2: SUPERMARKET | G2: AMARA OSEI | H2: 45292 | I2: 337 units | J2: ₦990.00 | K2: 0.12 | L2: PAID
A3: ORD-1002 | B3: PKG-002 | D3: Snacks | E3: South | F3: Wholesaler | G3: Tunde Bello | H3: 45293 | I3: 135 | J3: 350 | L3: Pending
A4: ORD-1003 | B4: PKG-003 | D4: Snacks | E4: East | F4: Online | G4: Ngozi Eze | H4: 45294 | I4: 387 | J4: 420 | L4: Paid
A5: ORD-1004 | B5: PKG-004 | D5: Beverages | E5: West | F5: Convenience Store | G5: Emeka Okafor | H5: 45295 | I5: 389 | J5: 1200 | K5: 0.03 | L5: Paid
A6: ORD-1005 | B6: PKG-005 | D6: Beverages | E6: Central | F6: Pharmacy | G6: Fatima Musa | H6: 45296 | I6: 226 | J6: 200 | L6: Pending
A7: ORD-1006 | B7: PKG-006 | D7: Baked Goods | E7: North | F7: Supermarket | G7: Chidi Nwosu | H7: 45297 | J7: 895 | L7: Paid | M7: 89500
A8: ORD-1007 | B8: PKG-007 | D8: Beverages | E8: South | F8: Wholesaler | G8: Amara Osei | H8: 45298 | I8: 268 | J8: 650 | K8: 0.09 | L8: Pending
A9: ORD-1008 | B9: PKG-008 | D9: Breakfast | E9: East | F9: Online | G9: Tunde Bello | H9: 45299 | I9: 376 | J9: 2800 | L9: Paid
A10: ORD-1009 | B10: PKG-009 | D10: Snacks | E10: West | F10: Convenience Store | G10: Ngozi Eze | H10: 45300 | I10: 289 | J10: 280 | L10: Paid
A11: ORD-1010 | B11: PKG-010 | D11: Baked Goods | E11: Central | F11: Pharmacy | G11: Emeka Okafor | H11: 45301 | I11: 239 | J11: 750 | K11: 0.13 | L11: Pending
A12: ORD-1011 | B12: PKG-001 | D12: Beverages | E12: North | F12: Supermarket | G12: Fatima Musa | H12: 45302 | I12: 13 | J12: 990 | L12: Paid
A13: ORD-1011 | B13: PKG-001 | D13: Beverages | E13: North | F13: Supermarket | G13: Fatima Musa | H13: 45303 | I13: 13 | J13: 990 | L13: Paid
A14: ORD-1012 | B14: PKG-002 | D14: Snacks | E14: South | F14: Wholesaler | G14: Chidi Nwosu | H14: 45304 | I14: 91 | J14: 350 | L14: Pending
A15: ORD-1013 | B15: PKG-003 | D15: Snacks | E15: East | F15: Online | G15: Amara Osei | H15: 45305 | I15: 184 | K15: 0.05 | L15: Paid
A16: ORD-1014 | B16: PKG-004 | D16: Beverages | E16: West | F16: Convenience Store | G16: Tunde Bello | H16: 45306 | I16: 400 | J16: 1200 | L16: Paid
A17: ORD-1015 | B17: PKG-005 | D17: Beverages | E17: Central | F17: Pharmacy | G17: Ngozi Eze | H17: 45307 | I17: 57 | J17: 200 | L17: Pending
A18: ORD-1016 | B18: PKG-006 | D18: Baked Goods | E18: North | F18: Supermarket | G18: Emeka Okafor | H18: 45308 | I18: 193 | J18: 895 | K18: 0.1 | L18: Paid
A19: ORD-1017 | B19: PKG-007 | D19: Beverages | E19: South | F19: Wholesaler | G19: Fatima Musa | H19: 45309 | I19: 423 | J19: 650 | L19: Pending
A20: ORD-1018 | B20: PKG-008 | D20: BREAKFAST | E20: EAST | F20: ONLINE | G20: CHIDI NWOSU | H20: 45310 | I20: 245 | J20: 2800 | L20: PAID
A21: ORD-1019 | B21: PKG-009 | D21: Snacks | E21: West | F21: Convenience Store | G21: Amara Osei | H21: 45311 | I21: 482 | J21: 280 | K21: 0.09 | L21: Paid
A22: ORD-1020 | B22: PKG-010 | D22: Baked Goods | E22: Central | F22: Pharmacy | G22: Tunde Bello | H22: 45312 | I22: 434 | J22: ₦750.00 | L22: Pending
A23: ORD-1021 | B23: PKG-001 | D23: Beverages | E23: North | F23: Supermarket | G23: Ngozi Eze | H23: 45313 | I23: 463 | J23: 990 | L23: Paid
A24: ORD-1022 | B24: PKG-002 | D24: Snacks | E24: South | F24: Wholesaler | G24: Emeka Okafor | H24: 45314 | I24: 305 | J24: 350 | K24: 0.03 | L24: Pending
A25: ORD-1023 | B25: PKG-003 | D25: Snacks | E25: East | F25: Online | G25: Fatima Musa | H25: 45315 | J25: 420 | L25: Paid | M25: 63000
A26: ORD-1024 | B26: PKG-004 | D26: beverages | E26: west | F26: convenience store | G26: chidi nwosu | H26: 45316 | I26: 158 | J26: 1200 | L26: paid
A27: ORD-1025 | B27: PKG-005 | D27: Beverages | E27: Central | F27: Pharmacy | G27: Amara Osei | H27: 45317 | I27: 447 | J27: 200 | K27: 0.03 | L27: Pending
A28: ORD-1026 | B28: PKG-006 | D28: Baked Goods | E28: North | F28: Supermarket | G28: Tunde Bello | H28: 45318 | I28: 152 units | J28: 895 | L28: Paid
A29: ORD-1027 | B29: PKG-007 | D29: Beverages | E29: South | F29: Wholesaler | G29: Ngozi Eze | H29: 45319 | I29: 437 | J29: 650 | L29: Pending
A30: ORD-1028 | B30: PKG-008 | D30: Breakfast | E30: East | F30: Online | G30: Emeka Okafor | H30: 45320 | I30: 199 | J30: 2800 | K30: 0.11 | L30: Paid
A31: ORD-1029 | B31: PKG-009 | D31: Snacks | E31: West | F31: Convenience Store | G31: Fatima Musa | H31: 45321 | I31: 369 | J31: 280 | L31: Paid
A32: ORD-1030 | B32: PKG-010 | D32: Baked Goods | E32: Central | F32: Pharmacy | G32: Chidi Nwosu | H32: 45322 | I32: 341 | J32: 750 | L32: Pending
A33: ORD-1031 | B33: PKG-001 | D33: Beverages | E33: North | F33: Supermarket | G33: Amara Osei | H33: 45323 | I33: 335 | J33: 990 | K33: 0.11 | L33: Paid
A34: ORD-1032 | B34: PKG-002 | D34: Snacks | E34: South | F34: Wholesaler | G34: Tunde Bello | H34: 45324 | I34: 93 | J34: 350 | L34: Pending
A35: ORD-1033 | B35: PKG-003 | D35: Snacks | E35: East | F35: Online | G35: Ngozi Eze | H35: 45325 | I35: 148 | J35: 420 | L35: Paid
A36: ORD-1034 | B36: PKG-004 | D36: Beverages | E36: West | F36: Convenience Store | G36: Emeka Okafor | H36: 45326 | I36: 337 | J36: 1200 | K36: 0.05 | L36: Paid
A37: ORD-1035 | B37: PKG-005 | D37: BEVERAGES | E37: CENTRAL | F37: PHARMACY | G37: FATIMA MUSA | H37: 45327 | I37: 176 | J37: 200 | L37: PENDING
A38: ORD-1036 | B38: PKG-006 | D38: Baked Goods | E38: North | F38: Supermarket | G38: Chidi Nwosu | H38: 45328 | I38: 407 | J38: 895 | L38: Paid
A39: ORD-1037 | B39: PKG-007 | D39: Beverages | E39: South | F39: Wholesaler | G39: Amara Osei | H39: 45329 | I39: 430 | J39: 650 | K39: 0.06 | L39: Pending
A40: ORD-1038 | B40: PKG-008 | D40: Breakfast | E40: East | F40: Online | G40: Tunde Bello | H40: 45330 | I40: 147 | J40: 2800 | L40: Paid
A41: ORD-1039 | B41: PKG-009 | D41: Snacks | E41: West | F41: Convenience Store | G41: Ngozi Eze | H41: 45331 | J41: ₦280.00 | L41: Paid | M41: 17640
A42: ORD-1040 | B42: PKG-010 | D42: Baked Goods | E42: Central | F42: Pharmacy | G42: Emeka Okafor | H42: 45332 | I42: 458 | J42: 750 | K42: 0.05 | L42: Pending
A43: ORD-1041 | B43: PKG-001 | D43: Beverages | E43: North | F43: Supermarket | G43: Fatima Musa | H43: 45333 | I43: 265 | J43: 990 | L43: Paid
A44: ORD-1042 | B44: PKG-002 | D44: Snacks | E44: South | F44: Wholesaler | G44: Chidi Nwosu | H44: 45334 | I44: 478 | J44: 350 | L44: Pending
A45: ORD-1043 | B45: PKG-003 | D45: Snacks | E45: East | F45: Online | G45: Amara Osei | H45: 45335 | I45: 83 | J45: 420 | K45: 0.05 | L45: Paid
A46: ORD-1044 | B46: PKG-004 | D46: Beverages | E46: West | F46: Convenience Store | G46: Tunde Bello | H46: 45336 | I46: 297 | J46: 1200 | L46: Paid
A47: ORD-1045 | B47: PKG-005 | D47: Beverages | E47: Central | F47: Pharmacy | G47: Ngozi Eze | H47: 45337 | I47: 392 | L47: Pending
A48: ORD-1046 | B48: PKG-006 | D48: Baked Goods | E48: North | F48: Supermarket | G48: Emeka Okafor | H48: 45338 | I48: 469 | J48: 895 | K48: 0.07 | L48: Paid
A49: ORD-1046 | B49: PKG-006 | D49: Baked Goods | E49: North | F49: Supermarket | G49: Emeka Okafor | H49: 45339 | I49: 469 | J49: 895 | K49: 0.07 | L49: Paid
A50: ORD-1047 | B50: PKG-007 | D50: beverages | E50: south | F50: wholesaler | G50: fatima musa | H50: 45340 | I50: 80 | J50: 650 | L50: pending
A51: ORD-1048 | B51: PKG-008 | D51: Breakfast | E51: East | F51: Online | G51: Chidi Nwosu | H51: 45341 | I51: 56 | J51: 2800 | L51: Paid
A52: ORD-1049 | B52: PKG-009 | D52: Snacks | E52: West | F52: Convenience Store | G52: Amara Osei | H52: 45342 | I52: 450 | J52: 280 | K52: 0.1 | L52: Paid
A53: ORD-1050 | B53: PKG-010 | D53: Baked Goods | E53: Central | F53: Pharmacy | G53: Tunde Bello | H53: 45343 | I53: 415 | J53: 750 | L53: Pending
A54: ORD-1051 | B54: PKG-001 | D54: Beverages | E54: North | F54: Supermarket | G54: Ngozi Eze | H54: 45344 | I54: 315 units | J54: 990 | L54: Paid
A55: ORD-1052 | B55: PKG-002 | D55: SNACKS | E55: SOUTH | F55: WHOLESALER | G55: EMEKA OKAFOR | H55: 45345 | I55: 205 | J55: 350 | K55: 0.08 | L55: PENDING
A56: ORD-1053 | B56: PKG-003 | D56: Snacks | E56: East | F56: Online | G56: Fatima Musa | H56: 45346 | I56: 138 | J56: 420 | L56: Paid
A57: ORD-1054 | B57: PKG-004 | D57: Beverages | E57: West | F57: Convenience Store | G57: Chidi Nwosu | H57: 45347 | I57: 450 | J57: 1200 | L57: Paid
A58: ORD-1055 | B58: PKG-005 | D58: Beverages | E58: Central | F58: Pharmacy | G58: Amara Osei | H58: 45348 | I58: 358 | J58: 200 | K58: 0.11 | L58: Pending
A59: ORD-1056 | B59: PKG-006 | D59: Baked Goods | E59: North | F59: Supermarket | G59: Tunde Bello | H59: 45349 | J59: 895 | L59: Paid | M59: 143200
A60: ORD-1057 | B60: PKG-007 | D60: Beverages | E60: South | F60: Wholesaler | G60: Ngozi Eze | H60: 45350 | I60: 403 | J60: 650 | L60: Pending
A61: ORD-1058 | B61: PKG-008 | D61: Breakfast | E61: East | F61: Online | G61: Emeka Okafor | H61: 45351 | I61: 67 | J61: ₦2800.00 | K61: 0.04 | L61: Paid
A62: ORD-1059 | B62: PKG-009 | D62: Snacks | E62: West | F62: Convenience Store | G62: Fatima Musa | H62: 45352 | I62: 11 | J62: 280 | L62: Paid
A63: ORD-1060 | B63: PKG-010 | D63: Baked Goods | E63: Central | F63: Pharmacy | G63: Chidi Nwosu | H63: 45353 | I63: 458 | J63: 750 | L63: Pending
A64: ORD-1061 | B64: PKG-001 | D64: Beverages | E64: North | F64: Supermarket | G64: Amara Osei | H64: 45354 | I64: 266 | J64: 990 | K64: 0.09 | L64: Paid
A65: ORD-1062 | B65: PKG-002 | D65: Snacks | E65: South | F65: Wholesaler | G65: Tunde Bello | H65: 45355 | I65: 64 | J65: 350 | L65: Pending
A66: ORD-1063 | B66: PKG-003 | D66: Snacks | E66: East | F66: Online | G66: Ngozi Eze | H66: 45356 | I66: 162 | J66: 420 | L66: Paid
A67: ORD-1064 | B67: PKG-004 | D67: Beverages | E67: West | F67: Convenience Store | G67: Emeka Okafor | H67: 45357 | I67: 269 | J67: 1200 | K67: 0.04 | L67: Paid
A68: ORD-1065 | B68: PKG-005 | D68: Beverages | E68: Central | F68: Pharmacy | G68: Fatima Musa | H68: 45358 | I68: 400 | J68: 200 | L68: Pending
A69: ORD-1066 | B69: PKG-006 | D69: Baked Goods | E69: North | F69: Supermarket | G69: Chidi Nwosu | H69: 45359 | I69: 498 | J69: 895 | L69: Paid
A70: ORD-1067 | B70: PKG-007 | D70: Beverages | E70: South | F70: Wholesaler | G70: Amara Osei | H70: 45360 | I70: 281 | J70: 650 | K70: 0.1 | L70: Pending
A71: ORD-1068 | B71: PKG-008 | D71: Breakfast | E71: East | F71: Online | G71: Tunde Bello | H71: 45361 | I71: 260 | L71: Paid
A72: ORD-1069 | B72: PKG-009 | D72: SNACKS | E72: WEST | F72: CONVENIENCE STORE | G72: NGOZI EZE | H72: 45362 | I72: 485 | J72: 280 | L72: PAID
A73: ORD-1070 | B73: PKG-010 | D73: baked goods | E73: central | F73: pharmacy | G73: emeka okafor | H73: 45363 | I73: 435 | J73: 750 | K73: 0.05 | L73: pending
A74: ORD-1071 | B74: PKG-001 | D74: Beverages | E74: North | F74: Supermarket | G74: Fatima Musa | H74: 45364 | I74: 133 | J74: 990 | L74: Paid
A75: ORD-1072 | B75: PKG-002 | D75: Snacks | E75: South | F75: Wholesaler | G75: Chidi Nwosu | H75: 45365 | J75: 350 | L75: Pending | M75: 31150
A76: ORD-1073 | B76: PKG-003 | D76: Snacks | E76: East | F76: Online | G76: Amara Osei | H76: 45366 | I76: 384 | J76: 420 | K76: 0.03 | L76: Paid
A77: ORD-1074 | B77: PKG-004 | D77: Beverages | E77: West | F77: Convenience Store | G77: Tunde Bello | H77: 45367 | I77: 399 | J77: 1200 | L77: Paid
A78: ORD-1075 | B78: PKG-005 | D78: Beverages | E78: Central | F78: Pharmacy | G78: Ngozi Eze | H78: 45368 | I78: 74 | J78: 200 | L78: Pending
A79: ORD-1076 | B79: PKG-006 | D79: Baked Goods | E79: North | F79: Supermarket | G79: Emeka Okafor | H79: 45369 | I79: 253 units | J79: 895 | K79: 0.04 | L79: Paid
A80: ORD-1077 | B80: PKG-007 | D80: Beverages | E80: South | F80: Wholesaler | G80: Fatima Musa | H80: 45370 | I80: 280 | J80: ₦650.00 | L80: Pending
A81: ORD-1078 | B81: PKG-008 | D81: Breakfast | E81: East | F81: Online | G81: Chidi Nwosu | H81: 45371 | I81: 226 | J81: 2800 | L81: Paid
A82: ORD-1079 | B82: PKG-009 | D82: Snacks | E82: West | F82: Convenience Store | G82: Amara Osei | H82: 45372 | I82: 485 | J82: 280 | K82: 0.11 | L82: Paid
A83: ORD-1080 | B83: PKG-010 | D83: Baked Goods | E83: Central | F83: Pharmacy | G83: Tunde Bello | H83: 45373 | I83: 112 | J83: 750 | L83: Pending
A84: ORD-1081 | B84: PKG-001 | D84: Beverages | E84: North | F84: Supermarket | G84: Ngozi Eze | H84: 45374 | I84: 214 | J84: 990 | L84: Paid
A85: ORD-1082 | B85: PKG-002 | D85: Snacks | E85: South | F85: Wholesaler | G85: Emeka Okafor | H85: 45375 | I85: 342 | J85: 350 | K85: 0.14 | L85: Pending
A86: ORD-1083 | B86: PKG-003 | D86: Snacks | E86: East | F86: Online | G86: Fatima Musa | H86: 45376 | I86: 241 | J86: 420 | L86: Paid
A87: ORD-1084 | B87: PKG-004 | D87: Beverages | E87: West | F87: Convenience Store | G87: Chidi Nwosu | H87: 45377 | I87: 125 | J87: 1200 | L87: Paid
A88: ORD-1085 | B88: PKG-005 | D88: Beverages | E88: Central | F88: Pharmacy | G88: Amara Osei | H88: 45378 | I88: 20 | J88: 200 | K88: 0.05 | L88: Pending
A89: ORD-1086 | B89: PKG-006 | D89: BAKED GOODS | E89: NORTH | F89: SUPERMARKET | G89: TUNDE BELLO | H89: 45379 | I89: 122 | J89: 895 | L89: PAID
A90: ORD-1086 | B90: PKG-006 | D90: BAKED GOODS | E90: NORTH | F90: SUPERMARKET | G90: TUNDE BELLO | H90: 45380 | I90: 122 | J90: 895 | L90: PAID
A91: ORD-1087 | B91: PKG-008 | D91: Breakfast | E91: East | F91: Online | G91: Tunde Bello | H91: 45381 | I91: 120 | J91: 2800 | K91: 0.02 | L91: Paid
A92: ORD-1088 | B92: PKG-008 | D92: Breakfast | E92: East | F92: Online | G92: Emeka Okafor | H92: 45382 | I92: 127 | J92: 2800 | K92: 0.02 | L92: Paid
A93: ORD-1089 | B93: PKG-009 | D93: Snacks | E93: West | F93: Convenience Store | G93: Fatima Musa | H93: 45383 | I93: 179 | L93: Paid
A94: ORD-1090 | B94: PKG-010 | D94: Baked Goods | E94: Central | F94: Pharmacy | G94: Chidi Nwosu | H94: 45384 | J94: 750 | L94: Pending | M94: 83250
A95: ORD-1091 | B95: PKG-001 | D95: Beverages | E95: North | F95: Supermarket | G95: Amara Osei | H95: 45385 | I95: 258 | J95: 990 | K95: 0.04 | L95: Paid
A96: ORD-1092 | B96: PKG-002 | D96: Snacks | E96: South | F96: Wholesaler | G96: Tunde Bello | H96: 45386 | I96: 488 | J96: 350 | L96: Pending
A97: ORD-1093 | B97: PKG-003 | D97: snacks | E97: east | F97: online | G97: ngozi eze | H97: 45387 | I97: 305 | J97: 420 | L97: paid
A98: ORD-1094 | B98: PKG-004 | D98: Beverages | E98: West | F98: Convenience Store | G98: Emeka Okafor | H98: 45388 | I98: 411 | J98: 1200 | K98: 0.07 | L98: Paid
A99: ORD-1095 | B99: PKG-005 | D99: Beverages | E99: Central | F99: Pharmacy | G99: Fatima Musa | H99: 45389 | I99: 58 | J99: 200 | L99: Pending
A100: ORD-1096 | B100: PKG-006 | D100: Baked Goods | E100: North | F100: Supermarket | G100: Chidi Nwosu | H100: 45390 | I100: 230 | J100: ₦895.0 | L100: Paid
...

Sheet Product_Lookup
A1: Product ID | B1: Product Name | C1: Category | D1: Unit Price (₦) | E1: Category Code
A2: PKG-009 | B2: CrispBite Corn Chips 100g | C2: Snacks | D2: 280 | E2: SNK
A3: PKG-003 | B3: CrispBite Potato Chips 150g | C3: Snacks | D3: 420 | E3: SNK
A4: PKG-004 | B4: DailyBrew Green Tea 25 bags | C4: Beverages | D4: 1200 | E4: BEV
A5: PKG-007 | B5: FreshSip Mango Juice 500ml | C5: Beverages | D5: 650 | E5: BEV
A6: PKG-001 | B6: FreshSip Orange Juice 1L | C6: Beverages | D6: 990 | E6: BEV
A7: PKG-006 | B7: GoldenBite Biscuits 200g | C7: Baked Goods | D7: 895 | E7: BAK
A8: PKG-010 | B8: GoldenBite Chocolate Cookies 150g | C8: Baked Goods | D8: 750 | E8: BAK
A9: PKG-005 | B9: HealthPure Bottled Water 500ml | C9: Beverages | D9: 200 | E9: BEV
A10: PKG-008 | B10: NutriMix Cereal Box 500g | C10: Breakfast | D10: 2800 | E10: BRK
A11: PKG-002 | B11: NutriMix Granola Bar | C11: Snacks | D11: 350 | E11: SNK
A12: PKG-011 | B12: NouraMart Protein Bar 60g | C12: Snacks | D12: 680 | E12: SNK
A13: PKG-012 | B13: ZestSip Citrus Drink 350ml | C13: Beverages | D13: 450 | E13: BEV
A14: PKG-013 | B14: GoldenBite Oat Cookies 180g | C14: Baked Goods | D14: 820 | E14: BAK

Sheet Clean_data
A1: Order ID | B1: Product ID | C1: Product Name | D1: Category | E1: Region | F1: Sales Channel | G1: Sales Rep | H1: Order Date | I1: Units Sold | J1: Unit Price (₦) | K1: Discount (%) | L1: Payment Status | M1: Total Sales (₦) | N1: Net Revenue (₦) | O1: Revenue Tier
A2: ORD-1001 | B2: PKG-001 | C2: FreshSip Orange Juice 1L | D2: Beverages | E2: North | F2: Supermarket | G2: Amara Osei | H2: 45292 | I2: 337 | J2: 990 | K2: 0.12 | L2: Paid | M2: =old_data[[#This Row],[Units Sold]]*old_data[[#This Row],[Unit Price (₦)]] -> 333630 | N2: =old_data[[#This Row],[Total Sales (₦)]]*(1-old_data[[#This Row],[Discount (%)]]) -> 293594.4 | O2: =IF(old_data[[#This Row],[Net Revenue (₦)]]>350000,"High",IF(old_data[[#This Row],[Net Revenue (₦)]]>100000,"Medium","Low")) -> Medium
A3: ORD-1002 | B3: PKG-002 | C3: NutriMix Granola Bar | D3: Snacks | E3: South | F3: Wholesaler | G3: Tunde Bello | H3: 45293 | I3: 135 | J3: 350 | K3: 0 | L3: Pending | M3: =old_data[[#This Row],[Units Sold]]*old_data[[#This Row],[Unit Price (₦)]] -> 47250 | N3: =old_data[[#This Row],[Total Sales (₦)]]*(1-old_data[[#This Row],[Discount (%)]]) -> 47250 | O3: =IF(old_data[[#This Row],[Net Revenue (₦)]]>350000,"High",IF(old_data[[#This Row],[Net Revenue (₦)]]>100000,"Medium","Low")) -> Low
A4: ORD-1003 | B4: PKG-003 | C4: CrispBite Potato Chips 150g | D4: Snacks | E4: East | F4: Online | G4: Ngozi Eze | H4: 45294 | I4: 387 | J4: 420 | K4: 0 | L4: Paid | M4: =old_data[[#This Row],[Units Sold]]*old_data[[#This Row],[Unit Price (₦)]] -> 162540 | N4: =old_data[[#This Row],[Total Sales (₦)]]*(1-old_data[[#This Row],[Discount (%)]]) -> 162540 | O4: =IF(old_data[[#This Row],[Net Revenue (₦)]]>350000,"High",IF(old_data[[#This Row],[Net Revenue (₦)]]>100000,"Medium","Low")) -> Medium
A5: ORD-1004 | B5: PKG-004 | C5: DailyBrew Green Tea 25 bags | D5: Beverages | E5: West | F5: Convenience Store | G5: Emeka Okafor | H5: 45295 | I5: 389 | J5: 1200 | K5: 0.03 | L5: Paid | M5: =old_data[[#This Row],[Units Sold]]*old_data[[#This Row],[Unit Price (₦)]] -> 466800 | N5: =old_data[[#This Row],[Total Sales (₦)]]*(1-old_data[[#This Row],[Discount (%)]]) -> 452796 | O5: =IF(old_data[[#This Row],[Net Revenue (₦)]]>350000,"High",IF(old_data[[#This Row],[Net Revenue (₦)]]>100000,"Medium","Low")) -> High
A6: ORD-1005 | B6: PKG-005 | C6: HealthPure Bottled Water 500ml | D6: Beverages | E6: Central | F6: Pharmacy | G6: Fatima Musa | H6: 45296 | I6: 226 | J6: 200 | K6: 0 | L6: Pending | M6: =old_data[[#This Row],[Units Sold]]*old_data[[#This Row],[Unit Price (₦)]] -> 45200 | N6: =old_data[[#This Row],[Total Sales (₦)]]*(1-old_data[[#This Row],[Discount (%)]]) -> 45200 | O6: =IF(old_data[[#This Row],[Net Revenue (₦)]]>350000,"High",IF(old_data[[#This Row],[Net Revenue (₦)]]>100000,"Medium","Low")) -> Low
A7: ORD-1006 | B7: PKG-006 | C7: GoldenBite Biscuits 200g | D7: Baked Goods | E7: North | F7: Supermarket | G7: Chidi Nwosu | H7: 45297 | I7: 100 | J7: 895 | K7: 0 | L7: Paid | M7: 89500 | N7: =old_data[[#This Row],[Total Sales (₦)]]*(1-old_data[[#This Row],[Discount (%)]]) -> 89500 | O7: =IF(old_data[[#This Row],[Net Revenue (₦)]]>350000,"High",IF(old_data[[#This Row],[Net Revenue (₦)]]>100000,"Medium","Low")) -> Low
A8: ORD-1007 | B8: PKG-007 | C8: FreshSip Mango Juice 500ml | D8: Beverages | E8: South | F8: Wholesaler | G8: Amara Osei | H8: 45298 | I8: 268 | J8: 650 | K8: 0.09 | L8: Pending | M8: =old_data[[#This Row],[Units Sold]]*old_data[[#This Row],[Unit Price (₦)]] -> 174200 | N8: =old_data[[#This Row],[Total Sales (₦)]]*(1-old_data[[#This Row],[Discount (%)]]) -> 158522 | O8: =IF(old_data[[#This Row],[Net Revenue (₦)]]>350000,"High",IF(old_data[[#This Row],[Net Revenue (₦)]]>100000,"Medium","Low")) -> Medium
A9: ORD-1008 | B9: PKG-008 | C9: NutriMix Cereal Box 500g | D9: Breakfast | E9: East | F9: Online | G9: Tunde Bello | H9: 45299 | I9: 376 | J9: 2800 | K9: 0 | L9: Paid | M9: =old_data[[#This Row],[Units Sold]]*old_data[[#This Row],[Unit Price (₦)]] -> 1052800 | N9: =old_data[[#This Row],[Total Sales (₦)]]*(1-old_data[[#This Row],[Discount (%)]]) -> 1052800 | O9: =IF(old_data[[#This Row],[Net Revenue (₦)]]>350000,"High",IF(old_data[[#This Row],[Net Revenue (₦)]]>100000,"Medium","Low")) -> High
A10: ORD-1009 | B10: PKG-009 | C10: CrispBite Corn Chips 100g | D10: Snacks | E10: West | F10: Convenience Store | G10: Ngozi Eze | H10: 45300 | I10: 289 | J10: 280 | K10: 0 | L10: Paid | M10: =old_data[[#This Row],[Units Sold]]*old_data[[#This Row],[Unit Price (₦)]] -> 80920 | N10: =old_data[[#This Row],[Total Sales (₦)]]*(1-old_data[[#This Row],[Discount (%)]]) -> 80920 | O10: =IF(old_data[[#This Row],[Net Revenue (₦)]]>350000,"High",IF(old_data[[#This Row],[Net Revenue (₦)]]>100000,"Medium","Low")) -> Low
A11: ORD-1010 | B11: PKG-010 | C11: GoldenBite Chocolate Cookies 150g | D11: Baked Goods | E11: Central | F11: Pharmacy | G11: Emeka Okafor | H11: 45301 | I11: 239 | J11: 750 | K11: 0.13 | L11: Pending | M11: =old_data[[#This Row],[Units Sold]]*old_data[[#This Row],[Unit Price (₦)]] -> 179250 | N11: =old_data[[#This Row],[Total Sales (₦)]]*(1-old_data[[#This Row],[Discount (%)]]) -> 155947.5 | O11: =IF(old_data[[#This Row],[Net Revenue (₦)]]>350000,"High",IF(old_data[[#This Row],[Net Revenue (₦)]]>100000,"Medium","Low")) -> Medium
A12: ORD-1011 | B12: PKG-001 | C12: FreshSip Orange Juice 1L | D12: Beverages | E12: North | F12: Supermarket | G12: Fatima Musa | H12: 45302 | I12: 13 | J12: 990 | K12: 0 | L12: Paid | M12: =old_data[[#This Row],[Units Sold]]*old_data[[#This Row],[Unit Price (₦)]] -> 12870 | N12: =old_data[[#This Row],[Total Sales (₦)]]*(1-old_data[[#This Row],[Discount (%)]]) -> 12870 | O12: =IF(old_data[[#This Row],[Net Revenue (₦)]]>350000,"High",IF(old_data[[#This Row],[Net Revenue (₦)]]>100000,"Medium","Low")) -> Low
A13: ORD-1012 | B13: PKG-002 | C13: NutriMix Granola Bar | D13: Snacks | E13: South | F13: Wholesaler | G13: Chidi Nwosu | H13: 45304 | I13: 91 | J13: 350 | K13: 0 | L13: Pending | M13: =old_data[[#This Row],[Units Sold]]*old_data[[#This Row],[Unit Price (₦)]] -> 31850 | N13: =old_data[[#This Row],[Total Sales (₦)]]*(1-old_data[[#This Row],[Discount (%)]]) -> 31850 | O13: =IF(old_data[[#This Row],[Net Revenue (₦)]]>350000,"High",IF(old_data[[#This Row],[Net Revenue (₦)]]>100000,"Medium","Low")) -> Low
A14: ORD-1013 | B14: PKG-003 | C14: CrispBite Potato Chips 150g | D14: Snacks | E14: East | F14: Online | G14: Amara Osei | H14: 45305 | I14: 184 | J14: 420 | K14: 0.05 | L14: Paid | M14: =old_data[[#This Row],[Units Sold]]*old_data[[#This Row],[Unit Price (₦)]] -> 77280 | N14: =old_data[[#This Row],[Total Sales (₦)]]*(1-old_data[[#This Row],[Discount (%)]]) -> 73416 | O14: =IF(old_data[[#This Row],[Net Revenue (₦)]]>350000,"High",IF(old_data[[#This Row],[Net Revenue (₦)]]>100000,"Medium","Low")) -> Low
A15: ORD-1014 | B15: PKG-004 | C15: DailyBrew Green Tea 25 bags | D15: Beverages | E15: West | F15: Convenience Store | G15: Tunde Bello | H15: 45306 | I15: 400 | J15: 1200 | K15: 0 | L15: Paid | M15: =old_data[[#This Row],[Units Sold]]*old_data[[#This Row],[Unit Price (₦)]] -> 480000 | N15: =old_data[[#This Row],[Total Sales (₦)]]*(1-old_data[[#This Row],[Discount (%)]]) -> 480000 | O15: =IF(old_data[[#This Row],[Net Revenue (₦)]]>350000,"High",IF(old_data[[#This Row],[Net Revenue (₦)]]>100000,"Medium","Low")) -> High
A16: ORD-1015 | B16: PKG-005 | C16: HealthPure Bottled Water 500ml | D16: Beverages | E16: Central | F16: Pharmacy | G16: Ngozi Eze | H16: 45307 | I16: 57 | J16: 200 | K16: 0 | L16: Pending | M16: =old_data[[#This Row],[Units Sold]]*old_data[[#This Row],[Unit Price (₦)]] -> 11400 | N16: =old_data[[#This Row],[Total Sales (₦)]]*(1-old_data[[#This Row],[Discount (%)]]) -> 11400 | O16: =IF(old_data[[#This Row],[Net Revenue (₦)]]>350000,"High",IF(old_data[[#This Row],[Net Revenue (₦)]]>100000,"Medium","Low")) -> Low
A17: ORD-1016 | B17: PKG-006 | C17: GoldenBite Biscuits 200g | D17: Baked Goods | E17: North | F17: Supermarket | G17: Emeka Okafor | H17: 45308 | I17: 193 | J17: 895 | K17: 0.1 | L17: Paid | M17: =old_data[[#This Row],[Units Sold]]*old_data[[#This Row],[Unit Price (₦)]] -> 172735 | N17: =old_data[[#This Row],[Total Sales (₦)]]*(1-old_data[[#This Row],[Discount (%)]]) -> 155461.5 | O17: =IF(old_data[[#This Row],[Net Revenue (₦)]]>350000,"High",IF(old_data[[#This Row],[Net Revenue (₦)]]>100000,"Medium","Low")) -> Medium
A18: ORD-1017 | B18: PKG-007 | C18: FreshSip Mango Juice 500ml | D18: Beverages | E18: South | F18: Wholesaler | G18: Fatima Musa | H18: 45309 | I18: 423 | J18: 650 | K18: 0 | L18: Pending | M18: =old_data[[#This Row],[Units Sold]]*old_data[[#This Row],[Unit Price (₦)]] -> 274950 | N18: =old_data[[#This Row],[Total Sales (₦)]]*(1-old_data[[#This Row],[Discount (%)]]) -> 274950 | O18: =IF(old_data[[#This Row],[Net Revenue (₦)]]>350000,"High",IF(old_data[[#This Row],[Net Revenue (₦)]]>100000,"Medium","Low")) -> Medium
A19: ORD-1018 | B19: PKG-008 | C19: NutriMix Cereal Box 500g | D19: Breakfast | E19: East | F19: Online | G19: Chidi Nwosu | H19: 45310 | I19: 245 | J19: 2800 | K19: 0 | L19: Paid | M19: =old_data[[#This Row],[Units Sold]]*old_data[[#This Row],[Unit Price (₦)]] -> 686000 | N19: =old_data[[#This Row],[Total Sales (₦)]]*(1-old_data[[#This Row],[Discount (%)]]) -> 686000 | O19: =IF(old_data[[#This Row],[Net Revenue (₦)]]>350000,"High",IF(old_data[[#This Row],[Net Revenue (₦)]]>100000,"Medium","Low")) -> High
... A23: ORD-1022 | B23: PKG-002 | C23: NutriMix Granola Bar | D23: Snacks | E23: South | F23: Wholesaler | G23: Emeka Okafor | H23: 45314 | I23: 305 | J23: 350 | K23: 0.03 | L23: Pending | M23: =old_data[[#This Row],[Units Sold]]*old_data[[#This Row],[Unit Price (₦)]] -> 106750 | N23: =old_data[[#This Row],[Total Sales (₦)]]*(1-old_data[[#This Row],[Discount (%)]]) -> 103547.5 | O23: =IF(old_data[[#This Row],[Net Revenue (₦)]]>350000,"High",IF(old_data[[#This Row],[Net Revenue (₦)]]>100000,"Medium","Low")) -> Medium
A24: ORD-1023 | B24: PKG-003 | C24: CrispBite Potato Chips 150g | D24: Snacks | E24: East | F24: Online | G24: Fatima Musa | H24: 45315 | I24: 150 | J24: 420 | K24: 0 | L24: Paid | M24: 63000 | N24: =old_data[[#This Row],[Total Sales (₦)]]*(1-old_data[[#This Row],[Discount (%)]]) -> 63000 | O24: =IF(old_data[[#This Row],[Net Revenue (₦)]]>350000,"High",IF(old_data[[#This Row],[Net Revenue (₦)]]>100000,"Medium","Low")) -> Low
A25: ORD-1024 | B25: PKG-004 | C25: DailyBrew Green Tea 25 bags | D25: Beverages | E25: West | F25: Convenience Store | G25: Chidi Nwosu | H25: 45316 | I25: 158 | J25: 1200 | K25: 0 | L25: Paid | M25: =old_data[[#This Row],[Units Sold]]*old_data[[#This Row],[Unit Price (₦)]] -> 189600 | N25: =old_data[[#This Row],[Total Sales (₦)]]*(1-old_data[[#This Row],[Discount (%)]]) -> 189600 | O25: =IF(old_data[[#This Row],[Net Revenue (₦)]]>350000,"High",IF(old_data[[#This Row],[Net Revenue (₦)]]>100000,"Medium","Low")) -> Medium
A26: ORD-1025 | B26: PKG-005 | C26: HealthPure Bottled Water 500ml | D26: Beverages | E26: Central | F26: Pharmacy | G26: Amara Osei | H26: 45317 | I26: 447 | J26: 200 | K26: 0.03 | L26: Pending | M26: =old_data[[#This Row],[Units Sold]]*old_data[[#This Row],[Unit Price (₦)]] -> 89400 | N26: =old_data[[#This Row],[Total Sales (₦)]]*(1-old_data[[#This Row],[Discount (%)]]) -> 86718 | O26: =IF(old_data[[#This Row],[Net Revenue (₦)]]>350000,"High",IF(old_data[[#This Row],[Net Revenue (₦)]]>100000,"Medium","Low")) -> Low
A27: ORD-1026 | B27: PKG-006 | C27: GoldenBite Biscuits 200g | D27: Baked Goods | E27: North | F27: Supermarket | G27: Tunde Bello | H27: 45318 | I27: 152 | J27: 895 | K27: 0 | L27: Paid | M27: =old_data[[#This Row],[Units Sold]]*old_data[[#This Row],[Unit Price (₦)]] -> 136040 | N27: =old_data[[#This Row],[Total Sales (₦)]]*(1-old_data[[#This Row],[Discount (%)]]) -> 136040 | O27: =IF(old_data[[#This Row],[Net Revenue (₦)]]>350000,"High",IF(old_data[[#This Row],[Net Revenue (₦)]]>100000,"Medium","Low")) -> Medium
A28: ORD-1027 | B28: PKG-007 | C28: FreshSip Mango Juice 500ml | D28: Beverages | E28: South | F28: Wholesaler | G28: Ngozi Eze | H28: 45319 | I28: 437 | J28: 650 | K28: 0 | L28: Pending | M28: =old_data[[#This Row],[Units Sold]]*old_data[[#This Row],[Unit Price (₦)]] -> 284050 | N28: =old_data[[#This Row],[Total Sales (₦)]]*(1-old_data[[#This Row],[Discount (%)]]) -> 284050 | O28: =IF(old_data[[#This Row],[Net Revenue (₦)]]>350000,"High",IF(old_data[[#This Row],[Net Revenue (₦)]]>100000,"Medium","Low")) -> Medium
A29: ORD-1028 | B29: PKG-008 | C29: NutriMix Cereal Box 500g | D29: Breakfast | E29: East | F29: Online | G29: Emeka Okafor | H29: 45320 | I29: 199 | J29: 2800 | K29: 0.11 | L29: Paid | M29: =old_data[[#This Row],[Units Sold]]*old_data[[#This Row],[Unit Price (₦)]] -> 557200 | N29: =old_data[[#This Row],[Total Sales (₦)]]*(1-old_data[[#This Row],[Discount (%)]]) -> 495908 | O29: =IF(old_data[[#This Row],[Net Revenue (₦)]]>350000,"High",IF(old_data[[#This Row],[Net Revenue (₦)]]>100000,"Medium","Low")) -> High
A30: ORD-1029 | B30: PKG-009 | C30: CrispBite Corn Chips 100g | D30: Snacks | E30: West | F30: Convenience Store | G30: Fatima Musa | H30: 45321 | I30: 369 | J30: 280 | K30: 0 | L30: Paid | M30: =old_data[[#This Row],[Units Sold]]*old_data[[#This Row],[Unit Price (₦)]] -> 103320 | N30: =old_data[[#This Row],[Total Sales (₦)]]*(1-old_data[[#This Row],[Discount (%)]]) -> 103320 | O30: =IF(old_data[[#This Row],[Net Revenue (₦)]]>350000,"High",IF(old_data[[#This Row],[Net Revenue (₦)]]>100000,"Medium","Low")) -> Medium
A31: ORD-1030 | B31: PKG-010 | C31: GoldenBite Chocolate Cookies 150g | D31: Baked Goods | E31: Central | F31: Pharmacy | G31: Chidi Nwosu | H31: 45322 | I31: 341 | J31: 750 | K31: 0 | L31: Pending | M31: =old_data[[#This Row],[Units Sold]]*old_data[[#This Row],[Unit Price (₦)]] -> 255750 | N31: =old_data[[#This Row],[Total Sales (₦)]]*(1-old_data[[#This Row],[Discount (%)]]) -> 255750 | O31: =IF(old_data[[#This Row],[Net Revenue (₦)]]>350000,"High",IF(old_data[[#This Row],[Net Revenue (₦)]]>100000,"Medium","Low")) -> Medium
A32: ORD-1031 | B32: PKG-001 | C32: FreshSip Orange Juice 1L | D32: Beverages | E32: North | F32: Supermarket | G32: Amara Osei | H32: 45323 | I32: 335 | J32: 990 | K32: 0.11 | L32: Paid | M32: =old_data[[#This Row],[Units Sold]]*old_data[[#This Row],[Unit Price (₦)]] -> 331650 | N32: =old_data[[#This Row],[Total Sales (₦)]]*(1-old_data[[#This Row],[Discount (%)]]) -> 295168.5 | O32: =IF(old_data[[#This Row],[Net Revenue (₦)]]>350000,"High",IF(old_data[[#This Row],[Net Revenue (₦)]]>100000,"Medium","Low")) -> Medium
A33: ORD-1032 | B33: PKG-002 | C33: NutriMix Granola Bar | D33: Snacks | E33: South | F33: Wholesaler | G33: Tunde Bello | H33: 45324 | I33: 93 | J33: 350 | K33: 0 | L33: Pending | M33: =old_data[[#This Row],[Units Sold]]*old_data[[#This Row],[Unit Price (₦)]] -> 32550 | N33: =old_data[[#This Row],[Total Sales (₦)]]*(1-old_data[[#This Row],[Discount (%)]]) -> 32550 | O33: =IF(old_data[[#This Row],[Net Revenue (₦)]]>350000,"High",IF(old_data[[#This Row],[Net Revenue (₦)]]>100000,"Medium","Low")) -> Low
A34: ORD-1033 | B34: PKG-003 | C34: CrispBite Potato Chips 150g | D34: Snacks | E34: East | F34: Online | G34: Ngozi Eze | H34: 45325 | I34: 148 | J34: 420 | K34: 0 | L34: Paid | M34: =old_data[[#This Row],[Units Sold]]*old_data[[#This Row],[Unit Price (₦)]] -> 62160 | N34: =old_data[[#This Row],[Total Sales (₦)]]*(1-old_data[[#This Row],[Discount (%)]]) -> 62160 | O34: =IF(old_data[[#This Row],[Net Revenue (₦)]]>350000,"High",IF(old_data[[#This Row],[Net Revenue (₦)]]>100000,"Medium","Low")) -> Low
A35: ORD-1034 | B35: PKG-004 | C35: DailyBrew Green Tea 25 bags | D35: Beverages | E35: West | F35: Convenience Store | G35: Emeka Okafor | H35: 45326 | I35: 337 | J35: 1200 | K35: 0.05 | L35: Paid | M35: =old_data[[#This Row],[Units Sold]]*old_data[[#This Row],[Unit Price (₦)]] -> 404400 | N35: =old_data[[#This Row],[Total Sales (₦)]]*(1-old_data[[#This Row],[Discount (%)]]) -> 384180 | O35: =IF(old_data[[#This Row],[Net Revenue (₦)]]>350000,"High",IF(old_data[[#This Row],[Net Revenue (₦)]]>100000,"Medium","Low")) -> High
A36: ORD-1035 | B36: PKG-005 | C36: HealthPure Bottled Water 500ml | D36: Beverages | E36: Central | F36: Pharmacy | G36: Fatima Musa | H36: 45327 | I36: 176 | J36: 200 | K36: 0 | L36: Pending | M36: =old_data[[#This Row],[Units Sold]]*old_data[[#This Row],[Unit Price (₦)]] -> 35200 | N36: =old_data[[#This Row],[Total Sales (₦)]]*(1-old_data[[#This Row],[Discount (%)]]) -> 35200 | O36: =IF(old_data[[#This Row],[Net Revenue (₦)]]>350000,"High",IF(old_data[[#This Row],[Net Revenue (₦)]]>100000,"Medium","Low")) -> Low
... A39: ORD-1038 | B39: PKG-008 | C39: NutriMix Cereal Box 500g | D39: Breakfast | E39: East | F39: Online | G39: Tunde Bello | H39: 45330 | I39: 147 | J39: 2800 | K39: 0 | L39: Paid | M39: =old_data[[#This Row],[Units Sold]]*old_data[[#This Row],[Unit Price (₦)]] -> 411600 | N39: =old_data[[#This Row],[Total Sales (₦)]]*(1-old_data[[#This Row],[Discount (%)]]) -> 411600 | O39: =IF(old_data[[#This Row],[Net Revenue (₦)]]>350000,"High",IF(old_data[[#This Row],[Net Revenue (₦)]]>100000,"Medium","Low")) -> High
A40: ORD-1039 | B40: PKG-009 | C40: CrispBite Corn Chips 100g | D40: Snacks | E40: West | F40: Convenience Store | G40: Ngozi Eze | H40: 45331 | I40: 63 | J40: 280 | K40: 0 | L40: Paid | M40: 17640 | N40: =old_data[[#This Row],[Total Sales (₦)]]*(1-old_data[[#This Row],[Discount (%)]]) -> 17640 | O40: =IF(old_data[[#This Row],[Net Revenue (₦)]]>350000,"High",IF(old_data[[#This Row],[Net Revenue (₦)]]>100000,"Medium","Low")) -> Low
A41: ORD-1040 | B41: PKG-010 | C41: GoldenBite Chocolate Cookies 150g | D41: Baked Goods | E41: Central | F41: Pharmacy | G41: Emeka Okafor | H41: 45332 | I41: 458 | J41: 750 | K41: 0.05 | L41: Pending | M41: =old_data[[#This Row],[Units Sold]]*old_data[[#This Row],[Unit Price (₦)]] -> 343500 | N41: =old_data[[#This Row],[Total Sales (₦)]]*(1-old_data[[#This Row],[Discount (%)]]) -> 326325 | O41: =IF(old_data[[#This Row],[Net Revenue (₦)]]>350000,"High",IF(old_data[[#This Row],[Net Revenue (₦)]]>100000,"Medium","Low")) -> Medium
A42: ORD-1041 | B42: PKG-001 | C42: FreshSip Orange Juice 1L | D42: Beverages | E42: North | F42: Supermarket | G42: Fatima Musa | H42: 45333 | I42: 265 | J42: 990 | K42: 0 | L42: Paid | M42: =old_data[[#This Row],[Units Sold]]*old_data[[#This Row],[Unit Price (₦)]] -> 262350 | N42: =old_data[[#This Row],[Total Sales (₦)]]*(1-old_data[[#This Row],[Discount (%)]]) -> 262350 | O42: =IF(old_data[[#This Row],[Net Revenue (₦)]]>350000,"High",IF(old_data[[#This Row],[Net Revenue (₦)]]>100000,"Medium","Low")) -> Medium
A43: ORD-1042 | B43: PKG-002 | C43: NutriMix Granola Bar | D43: Snacks | E43: South | F43: Wholesaler | G43: Chidi Nwosu | H43: 45334 | I43: 478 | J43: 350 | K43: 0 | L43: Pending | M43: =old_data[[#This Row],[Units Sold]]*old_data[[#This Row],[Unit Price (₦)]] -> 167300 | N43: =old_data[[#This Row],[Total Sales (₦)]]*(1-old_data[[#This Row],[Discount (%)]]) -> 167300 | O43: =IF(old_data[[#This Row],[Net Revenue (₦)]]>350000,"High",IF(old_data[[#This Row],[Net Revenue (₦)]]>100000,"Medium","Low")) -> Medium
A44: ORD-1043 | B44: PKG-003 | C44: CrispBite Potato Chips 150g | D44: Snacks | E44: East | F44: Online | G44: Amara Osei | H44: 45335 | I44: 83 | J44: 420 | K44: 0.05 | L44: Paid | M44: =old_data[[#This Row],[Units Sold]]*old_data[[#This Row],[Unit Price (₦)]] -> 34860 | N44: =old_data[[#This Row],[Total Sales (₦)]]*(1-old_data[[#This Row],[Discount (%)]]) -> 33117 | O44: =IF(old_data[[#This Row],[Net Revenue (₦)]]>350000,"High",IF(old_data[[#This Row],[Net Revenue (₦)]]>100000,"Medium","Low")) -> Low
A45: ORD-1044 | B45: PKG-004 | C45: DailyBrew Green Tea 25 bags | D45: Beverages | E45: West | F45: Convenience Store | G45: Tunde Bello | H45: 45336 | I45: 297 | J45: 1200 | K45: 0 | L45: Paid | M45: =old_data[[#This Row],[Units Sold]]*old_data[[#This Row],[Unit Price (₦)]] -> 356400 | N45: =old_data[[#This Row],[Total Sales (₦)]]*(1-old_data[[#This Row],[Discount (%)]]) -> 356400 | O45: =IF(old_data[[#This Row],[Net Revenue (₦)]]>350000,"High",IF(old_data[[#This Row],[Net Revenue (₦)]]>100000,"Medium","Low")) -> High
A46: ORD-1045 | B46: PKG-005 | C46: HealthPure Bottled Water 500ml | D46: Beverages | E46: Central | F46: Pharmacy | G46: Ngozi Eze | H46: 45337 | I46: 392 | J46: 200 | K46: 0 | L46: Pending | M46: =old_data[[#This Row],[Units Sold]]*old_data[[#This Row],[Unit Price (₦)]] -> 78400 | N46: =old_data[[#This Row],[Total Sales (₦)]]*(1-old_data[[#This Row],[Discount (%)]]) -> 78400 | O46: =IF(old_data[[#This Row],[Net Revenue (₦)]]>350000,"High",IF(old_data[[#This Row],[Net Revenue (₦)]]>100000,"Medium","Low")) -> Low
A47: ORD-1046 | B47: PKG-006 | C47: GoldenBite Biscuits 200g | D47: Baked Goods | E47: North | F47: Supermarket | G47: Emeka Okafor | H47: 45338 | I47: 469 | J47: 895 | K47: 0.07 | L47: Paid | M47: =old_data[[#This Row],[Units Sold]]*old_data[[#This Row],[Unit Price (₦)]] -> 419755 | N47: =old_data[[#This Row],[Total Sales (₦)]]*(1-old_data[[#This Row],[Discount (%)]]) -> 390372.15 | O47: =IF(old_data[[#This Row],[Net Revenue (₦)]]>350000,"High",IF(old_data[[#This Row],[Net Revenue (₦)]]>100000,"Medium","Low")) -> High
A48: ORD-1047 | B48: PKG-007 | C48: FreshSip Mango Juice 500ml | D48: Beverages | E48: South | F48: Wholesaler | G48: Fatima Musa | H48: 45340 | I48: 80 | J48: 650 | K48: 0 | L48: Pending | M48: =old_data[[#This Row],[Units Sold]]*old_data[[#This Row],[Unit Price (₦)]] -> 52000 | N48: =old_data[[#This Row],[Total Sales (₦)]]*(1-old_data[[#This Row],[Discount (%)]]) -> 52000 | O48: =IF(old_data[[#This Row],[Net Revenue (₦)]]>350000,"High",IF(old_data[[#This Row],[Net Revenue (₦)]]>100000,"Medium","Low")) -> Low
A49: ORD-1048 | B49: PKG-008 | C49: NutriMix Cereal Box 500g | D49: Breakfast | E49: East | F49: Online | G49: Chidi Nwosu | H49: 45341 | I49: 56 | J49: 2800 | K49: 0 | L49: Paid | M49: =old_data[[#This Row],[Units Sold]]*old_data[[#This Row],[Unit Price (₦)]] -> 156800 | N49: =old_data[[#This Row],[Total Sales (₦)]]*(1-old_data[[#This Row],[Discount (%)]]) -> 156800 | O49: =IF(old_data[[#This Row],[Net Revenue (₦)]]>350000,"High",IF(old_data[[#This Row],[Net Revenue (₦)]]>100000,"Medium","Low")) -> Medium
A50: ORD-1049 | B50: PKG-009 | C50: CrispBite Corn Chips 100g | D50: Snacks | E50: West | F50: Convenience Store | G50: Amara Osei | H50: 45342 | I50: 450 | J50: 280 | K50: 0.1 | L50: Paid | M50: =old_data[[#This Row],[Units Sold]]*old_data[[#This Row],[Unit Price (₦)]] -> 126000 | N50: =old_data[[#This Row],[Total Sales (₦)]]*(1-old_data[[#This Row],[Discount (%)]]) -> 113400 | O50: =IF(old_data[[#This Row],[Net Revenue (₦)]]>350000,"High",IF(old_data[[#This Row],[Net Revenue (₦)]]>100000,"Medium","Low")) -> Medium
A51: ORD-1050 | B51: PKG-010 | C51: GoldenBite Chocolate Cookies 150g | D51: Baked Goods | E51: Central | F51: Pharmacy | G51: Tunde Bello | H51: 45343 | I51: 415 | J51: 750 | K51: 0 | L51: Pending | M51: =old_data[[#This Row],[Units Sold]]*old_data[[#This Row],[Unit Price (₦)]] -> 311250 | N51: =old_data[[#This Row],[Total Sales (₦)]]*(1-old_data[[#This Row],[Discount (%)]]) -> 311250 | O51: =IF(old_data[[#This Row],[Net Revenue (₦)]]>350000,"High",IF(old_data[[#This Row],[Net Revenue (₦)]]>100000,"Medium","Low")) -> Medium
A52: ORD-1051 | B52: PKG-001 | C52: FreshSip Orange Juice 1L | D52: Beverages | E52: North | F52: Supermarket | G52: Ngozi Eze | H52: 45344 | I52: 315 | J52: 990 | K52: 0 | L52: Paid | M52: =old_data[[#This Row],[Units Sold]]*old_data[[#This Row],[Unit Price (₦)]] -> 311850 | N52: =old_data[[#This Row],[Total Sales (₦)]]*(1-old_data[[#This Row],[Discount (%)]]) -> 311850 | O52: =IF(old_data[[#This Row],[Net Revenue (₦)]]>350000,"High",IF(old_data[[#This Row],[Net Revenue (₦)]]>100000,"Medium","Low")) -> Medium
... A56: ORD-1055 | B56: PKG-005 | C56: HealthPure Bottled Water 500ml | D56: Beverages | E56: Central | F56: Pharmacy | G56: Amara Osei | H56: 45348 | I56: 358 | J56: 200 | K56: 0.11 | L56: Pending | M56: =old_data[[#This Row],[Units Sold]]*old_data[[#This Row],[Unit Price (₦)]] -> 71600 | N56: =old_data[[#This Row],[Total Sales (₦)]]*(1-old_data[[#This Row],[Discount (%)]]) -> 63724 | O56: =IF(old_data[[#This Row],[Net Revenue (₦)]]>350000,"High",IF(old_data[[#This Row],[Net Revenue (₦)]]>100000,"Medium","Low")) -> Low
A57: ORD-1056 | B57: PKG-006 | C57: GoldenBite Biscuits 200g | D57: Baked Goods | E57: North | F57: Supermarket | G57: Tunde Bello | H57: 45349 | I57: 160 | J57: 895 | K57: 0 | L57: Paid | M57: 143200 | N57: =old_data[[#This Row],[Total Sales (₦)]]*(1-old_data[[#This Row],[Discount (%)]]) -> 143200 | O57: =IF(old_data[[#This Row],[Net Revenue (₦)]]>350000,"High",IF(old_data[[#This Row],[Net Revenue (₦)]]>100000,"Medium","Low")) -> Medium
A58: ORD-1057 | B58: PKG-007 | C58: FreshSip Mango Juice 500ml | D58: Beverages | E58: South | F58: Wholesaler | G58: Ngozi Eze | H58: 45350 | I58: 403 | J58: 650 | K58: 0 | L58: Pending | M58: =old_data[[#This Row],[Units Sold]]*old_data[[#This Row],[Unit Price (₦)]] -> 261950 | N58: =old_data[[#This Row],[Total Sales (₦)]]*(1-old_data[[#This Row],[Discount (%)]]) -> 261950 | O58: =IF(old_data[[#This Row],[Net Revenue (₦)]]>350000,"High",IF(old_data[[#This Row],[Net Revenue (₦)]]>100000,"Medium","Low")) -> Medium
A59: ORD-1058 | B59: PKG-008 | C59: NutriMix Cereal Box 500g | D59: Breakfast | E59: East | F59: Online | G59: Emeka Okafor | H59: 45351 | I59: 67 | J59: 2800 | K59: 0.04 | L59: Paid | M59: =old_data[[#This Row],[Units Sold]]*old_data[[#This Row],[Unit Price (₦)]] -> 187600 | N59: =old_data[[#This Row],[Total Sales (₦)]]*(1-old_data[[#This Row],[Discount (%)]]) -> 180096 | O59: =IF(old_data[[#This Row],[Net Revenue (₦)]]>350000,"High",IF(old_data[[#This Row],[Net Revenue (₦)]]>100000,"Medium","Low")) -> Medium
A60: ORD-1059 | B60: PKG-009 | C60: CrispBite Corn Chips 100g | D60: Snacks | E60: West | F60: Convenience Store | G60: Fatima Musa | H60: 45352 | I60: 11 | J60: 280 | K60: 0 | L60: Paid | M60: =old_data[[#This Row],[Units Sold]]*old_data[[#This Row],[Unit Price (₦)]] -> 3080 | N60: =old_data[[#This Row],[Total Sales (₦)]]*(1-old_data[[#This Row],[Discount (%)]]) -> 3080 | O60: =IF(old_data[[#This Row],[Net Revenue (₦)]]>350000,"High",IF(old_data[[#This Row],[Net Revenue (₦)]]>100000,"Medium","Low")) -> Low
A61: ORD-1060 | B61: PKG-010 | C61: GoldenBite Chocolate Cookies 150g | D61: Baked Goods | E61: Central | F61: Pharmacy | G61: Chidi Nwosu | H61: 45353 | I61: 458 | J61: 750 | K61: 0 | L61: Pending | M61: =old_data[[#This Row],[Units Sold]]*old_data[[#This Row],[Unit Price (₦)]] -> 343500 | N61: =old_data[[#This Row],[Total Sales (₦)]]*(1-old_data[[#This Row],[Discount (%)]]) -> 343500 | O61: =IF(old_data[[#This Row],[Net Revenue (₦)]]>350000,"High",IF(old_data[[#This Row],[Net Revenue (₦)]]>100000,"Medium","Low")) -> Medium
A62: ORD-1061 | B62: PKG-001 | C62: FreshSip Orange Juice 1L | D62: Beverages | E62: North | F62: Supermarket | G62: Amara Osei | H62: 45354 | I62: 266 | J62: 990 | K62: 0.09 | L62: Paid | M62: =old_data[[#This Row],[Units Sold]]*old_data[[#This Row],[Unit Price (₦)]] -> 263340 | N62: =old_data[[#This Row],[Total Sales (₦)]]*(1-old_data[[#This Row],[Discount (%)]]) -> 239639.4 | O62: =IF(old_data[[#This Row],[Net Revenue (₦)]]>350000,"High",IF(old_data[[#This Row],[Net Revenue (₦)]]>100000,"Medium","Low")) -> Medium
A63: ORD-1062 | B63: PKG-002 | C63: NutriMix Granola Bar | D63: Snacks | E63: South | F63: Wholesaler | G63: Tunde Bello | H63: 45355 | I63: 64 | J63: 350 | K63: 0 | L63: Pending | M63: =old_data[[#This Row],[Units Sold]]*old_data[[#This Row],[Unit Price (₦)]] -> 22400 | N63: =old_data[[#This Row],[Total Sales (₦)]]*(1-old_data[[#This Row],[Discount (%)]]) -> 22400 | O63: =IF(old_data[[#This Row],[Net Revenue (₦)]]>350000,"High",IF(old_data[[#This Row],[Net Revenue (₦)]]>100000,"Medium","Low")) -> Low
A64: ORD-1063 | B64: PKG-003 | C64: CrispBite Potato Chips 150g | D64: Snacks | E64: East | F64: Online | G64: Ngozi Eze | H64: 45356 | I64: 162 | J64: 420 | K64: 0 | L64: Paid | M64: =old_data[[#This Row],[Units Sold]]*old_data[[#This Row],[Unit Price (₦)]] -> 68040 | N64: =old_data[[#This Row],[Total Sales (₦)]]*(1-old_data[[#This Row],[Discount (%)]]) -> 68040 | O64: =IF(old_data[[#This Row],[Net Revenue (₦)]]>350000,"High",IF(old_data[[#This Row],[Net Revenue (₦)]]>100000,"Medium","Low")) -> Low
A65: ORD-1064 | B65: PKG-004 | C65: DailyBrew Green Tea 25 bags | D65: Beverages | E65: West | F65: Convenience Store | G65: Emeka Okafor | H65: 45357 | I65: 269 | J65: 1200 | K65: 0.04 | L65: Paid | M65: =old_data[[#This Row],[Units Sold]]*old_data[[#This Row],[Unit Price (₦)]] -> 322800 | N65: =old_data[[#This Row],[Total Sales (₦)]]*(1-old_data[[#This Row],[Discount (%)]]) -> 309888 | O65: =IF(old_data[[#This Row],[Net Revenue (₦)]]>350000,"High",IF(old_data[[#This Row],[Net Revenue (₦)]]>100000,"Medium","Low")) -> Medium
A66: ORD-1065 | B66: PKG-005 | C66: HealthPure Bottled Water 500ml | D66: Beverages | E66: Central | F66: Pharmacy | G66: Fatima Musa | H66: 45358 | I66: 400 | J66: 200 | K66: 0 | L66: Pending | M66: =old_data[[#This Row],[Units Sold]]*old_data[[#This Row],[Unit Price (₦)]] -> 80000 | N66: =old_data[[#This Row],[Total Sales (₦)]]*(1-old_data[[#This Row],[Discount (%)]]) -> 80000 | O66: =IF(old_data[[#This Row],[Net Revenue (₦)]]>350000,"High",IF(old_data[[#This Row],[Net Revenue (₦)]]>100000,"Medium","Low")) -> Low
A67: ORD-1066 | B67: PKG-006 | C67: GoldenBite Biscuits 200g | D67: Baked Goods | E67: North | F67: Supermarket | G67: Chidi Nwosu | H67: 45359 | I67: 498 | J67: 895 | K67: 0 | L67: Paid | M67: =old_data[[#This Row],[Units Sold]]*old_data[[#This Row],[Unit Price (₦)]] -> 445710 | N67: =old_data[[#This Row],[Total Sales (₦)]]*(1-old_data[[#This Row],[Discount (%)]]) -> 445710 | O67: =IF(old_data[[#This Row],[Net Revenue (₦)]]>350000,"High",IF(old_data[[#This Row],[Net Revenue (₦)]]>100000,"Medium","Low")) -> High
A68: ORD-1067 | B68: PKG-007 | C68: FreshSip Mango Juice 500ml | D68: Beverages | E68: South | F68: Wholesaler | G68: Amara Osei | H68: 45360 | I68: 281 | J68: 650 | K68: 0.1 | L68: Pending | M68: =old_data[[#This Row],[Units Sold]]*old_data[[#This Row],[Unit Price (₦)]] -> 182650 | N68: =old_data[[#This Row],[Total Sales (₦)]]*(1-old_data[[#This Row],[Discount (%)]]) -> 164385 | O68: =IF(old_data[[#This Row],[Net Revenue (₦)]]>350000,"High",IF(old_data[[#This Row],[Net Revenue (₦)]]>100000,"Medium","Low")) -> Medium
A69: ORD-1068 | B69: PKG-008 | C69: NutriMix Cereal Box 500g | D69: Breakfast | E69: East | F69: Online | G69: Tunde Bello | H69: 45361 | I69: 260 | J69: 2800 | K69: 0 | L69: Paid | M69: =old_data[[#This Row],[Units Sold]]*old_data[[#This Row],[Unit Price (₦)]] -> 728000 | N69: =old_data[[#This Row],[Total Sales (₦)]]*(1-old_data[[#This Row],[Discount (%)]]) -> 728000 | O69: =IF(old_data[[#This Row],[Net Revenue (₦)]]>350000,"High",IF(old_data[[#This Row],[Net Revenue (₦)]]>100000,"Medium","Low")) -> High
... A72: ORD-1071 | B72: PKG-001 | C72: FreshSip Orange Juice 1L | D72: Beverages | E72: North | F72: Supermarket | G72: Fatima Musa | H72: 45364 | I72: 133 | J72: 990 | K72: 0 | L72: Paid | M72: =old_data[[#This Row],[Units Sold]]*old_data[[#This Row],[Unit Price (₦)]] -> 131670 | N72: =old_data[[#This Row],[Total Sales (₦)]]*(1-old_data[[#This Row],[Discount (%)]]) -> 131670 | O72: =IF(old_data[[#This Row],[Net Revenue (₦)]]>350000,"High",IF(old_data[[#This Row],[Net Revenue (₦)]]>100000,"Medium","Low")) -> Medium
A73: ORD-1072 | B73: PKG-002 | C73: NutriMix Granola Bar | D73: Snacks | E73: South | F73: Wholesaler | G73: Chidi Nwosu | H73: 45365 | I73: 89 | J73: 350 | K73: 0 | L73: Pending | M73: 31150 | N73: =old_data[[#This Row],[Total Sales (₦)]]*(1-old_data[[#This Row],[Discount (%)]]) -> 31150 | O73: =IF(old_data[[#This Row],[Net Revenue (₦)]]>350000,"High",IF(old_data[[#This Row],[Net Revenue (₦)]]>100000,"Medium","Low")) -> Low
A74: ORD-1073 | B74: PKG-003 | C74: CrispBite Potato Chips 150g | D74: Snacks | E74: East | F74: Online | G74: Amara Osei | H74: 45366 | I74: 384 | J74: 420 | K74: 0.03 | L74: Paid | M74: =old_data[[#This Row],[Units Sold]]*old_data[[#This Row],[Unit Price (₦)]] -> 161280 | N74: =old_data[[#This Row],[Total Sales (₦)]]*(1-old_data[[#This Row],[Discount (%)]]) -> 156441.6 | O74: =IF(old_data[[#This Row],[Net Revenue (₦)]]>350000,"High",IF(old_data[[#This Row],[Net Revenue (₦)]]>100000,"Medium","Low")) -> Medium
A75: ORD-1074 | B75: PKG-004 | C75: DailyBrew Green Tea 25 bags | D75: Beverages | E75: West | F75: Convenience Store | G75: Tunde Bello | H75: 45367 | I75: 399 | J75: 1200 | K75: 0 | L75: Paid | M75: =old_data[[#This Row],[Units Sold]]*old_data[[#This Row],[Unit Price (₦)]] -> 478800 | N75: =old_data[[#This Row],[Total Sales (₦)]]*(1-old_data[[#This Row],[Discount (%)]]) -> 478800 | O75: =IF(old_data[[#This Row],[Net Revenue (₦)]]>350000,"High",IF(old_data[[#This Row],[Net Revenue (₦)]]>100000,"Medium","Low")) -> High
A76: ORD-1075 | B76: PKG-005 | C76: HealthPure Bottled Water 500ml | D76: Beverages | E76: Central | F76: Pharmacy | G76: Ngozi Eze | H76: 45368 | I76: 74 | J76: 200 | K76: 0 | L76: Pending | M76: =old_data[[#This Row],[Units Sold]]*old_data[[#This Row],[Unit Price (₦)]] -> 14800 | N76: =old_data[[#This Row],[Total Sales (₦)]]*(1-old_data[[#This Row],[Discount (%)]]) -> 14800 | O76: =IF(old_data[[#This Row],[Net Revenue (₦)]]>350000,"High",IF(old_data[[#This Row],[Net Revenue (₦)]]>100000,"Medium","Low")) -> Low
A77: ORD-1076 | B77: PKG-006 | C77: GoldenBite Biscuits 200g | D77: Baked Goods | E77: North | F77: Supermarket | G77: Emeka Okafor | H77: 45369 | I77: 253 | J77: 895 | K77: 0.04 | L77: Paid | M77: =old_data[[#This Row],[Units Sold]]*old_data[[#This Row],[Unit Price (₦)]] -> 226435 | N77: =old_data[[#This Row],[Total Sales (₦)]]*(1-old_data[[#This Row],[Discount (%)]]) -> 217377.6 | O77: =IF(old_data[[#This Row],[Net Revenue (₦)]]>350000,"High",IF(old_data[[#This Row],[Net Revenue (₦)]]>100000,"Medium","Low")) -> Medium
A78: ORD-1077 | B78: PKG-007 | C78: FreshSip Mango Juice 500ml | D78: Beverages | E78: South | F78: Wholesaler | G78: Fatima Musa | H78: 45370 | I78: 280 | J78: 650 | K78: 0 | L78: Pending | M78: =old_data[[#This Row],[Units Sold]]*old_data[[#This Row],[Unit Price (₦)]] -> 182000 | N78: =old_data[[#This Row],[Total Sales (₦)]]*(1-old_data[[#This Row],[Discount (%)]]) -> 182000 | O78: =IF(old_data[[#This Row],[Net Revenue (₦)]]>350000,"High",IF(old_data[[#This Row],[Net Revenue (₦)]]>100000,"Medium","Low")) -> Medium
A79: ORD-1078 | B79: PKG-008 | C79: NutriMix Cereal Box 500g | D79: Breakfast | E79: East | F79: Online | G79: Chidi Nwosu | H79: 45371 | I79: 226 | J79: 2800 | K79: 0 | L79: Paid | M79: =old_data[[#This Row],[Units Sold]]*old_data[[#This Row],[Unit Price (₦)]] -> 632800 | N79: =old_data[[#This Row],[Total Sales (₦)]]*(1-old_data[[#This Row],[Discount (%)]]) -> 632800 | O79: =IF(old_data[[#This Row],[Net Revenue (₦)]]>350000,"High",IF(old_data[[#This Row],[Net Revenue (₦)]]>100000,"Medium","Low")) -> High
A80: ORD-1079 | B80: PKG-009 | C80: CrispBite Corn Chips 100g | D80: Snacks | E80: West | F80: Convenience Store | G80: Amara Osei | H80: 45372 | I80: 485 | J80: 280 | K80: 0.11 | L80: Paid | M80: =old_data[[#This Row],[Units Sold]]*old_data[[#This Row],[Unit Price (₦)]] -> 135800 | N80: =old_data[[#This Row],[Total Sales (₦)]]*(1-old_data[[#This Row],[Discount (%)]]) -> 120862 | O80: =IF(old_data[[#This Row],[Net Revenue (₦)]]>350000,"High",IF(old_data[[#This Row],[Net Revenue (₦)]]>100000,"Medium","Low")) -> Medium
A81: ORD-1080 | B81: PKG-010 | C81: GoldenBite Chocolate Cookies 150g | D81: Baked Goods | E81: Central | F81: Pharmacy | G81: Tunde Bello | H81: 45373 | I81: 112 | J81: 750 | K81: 0 | L81: Pending | M81: =old_data[[#This Row],[Units Sold]]*old_data[[#This Row],[Unit Price (₦)]] -> 84000 | N81: =old_data[[#This Row],[Total Sales (₦)]]*(1-old_data[[#This Row],[Discount (%)]]) -> 84000 | O81: =IF(old_data[[#This Row],[Net Revenue (₦)]]>350000,"High",IF(old_data[[#This Row],[Net Revenue (₦)]]>100000,"Medium","Low")) -> Low
A82: ORD-1081 | B82: PKG-001 | C82: FreshSip Orange Juice 1L | D82: Beverages | E82: North | F82: Supermarket | G82: Ngozi Eze | H82: 45374 | I82: 214 | J82: 990 | K82: 0 | L82: Paid | M82: =old_data[[#This Row],[Units Sold]]*old_data[[#This Row],[Unit Price (₦)]] -> 211860 | N82: =old_data[[#This Row],[Total Sales (₦)]]*(1-old_data[[#This Row],[Discount (%)]]) -> 211860 | O82: =IF(old_data[[#This Row],[Net Revenue (₦)]]>350000,"High",IF(old_data[[#This Row],[Net Revenue (₦)]]>100000,"Medium","Low")) -> Medium
A83: ORD-1082 | B83: PKG-002 | C83: NutriMix Granola Bar | D83: Snacks | E83: South | F83: Wholesaler | G83: Emeka Okafor | H83: 45375 | I83: 342 | J83: 350 | K83: 0.14 | L83: Pending | M83: =old_data[[#This Row],[Units Sold]]*old_data[[#This Row],[Unit Price (₦)]] -> 119700 | N83: =old_data[[#This Row],[Total Sales (₦)]]*(1-old_data[[#This Row],[Discount (%)]]) -> 102942 | O83: =IF(old_data[[#This Row],[Net Revenue (₦)]]>350000,"High",IF(old_data[[#This Row],[Net Revenue (₦)]]>100000,"Medium","Low")) -> Medium
A84: ORD-1083 | B84: PKG-003 | C84: CrispBite Potato Chips 150g | D84: Snacks | E84: East | F84: Online | G84: Fatima Musa | H84: 45376 | I84: 241 | J84: 420 | K84: 0 | L84: Paid | M84: =old_data[[#This Row],[Units Sold]]*old_data[[#This Row],[Unit Price (₦)]] -> 101220 | N84: =old_data[[#This Row],[Total Sales (₦)]]*(1-old_data[[#This Row],[Discount (%)]]) -> 101220 | O84: =IF(old_data[[#This Row],[Net Revenue (₦)]]>350000,"High",IF(old_data[[#This Row],[Net Revenue (₦)]]>100000,"Medium","Low")) -> Medium
A85: ORD-1084 | B85: PKG-004 | C85: DailyBrew Green Tea 25 bags | D85: Beverages | E85: West | F85: Convenience Store | G85: Chidi Nwosu | H85: 45377 | I85: 125 | J85: 1200 | K85: 0 | L85: Paid | M85: =old_data[[#This Row],[Units Sold]]*old_data[[#This Row],[Unit Price (₦)]] -> 150000 | N85: =old_data[[#This Row],[Total Sales (₦)]]*(1-old_data[[#This Row],[Discount (%)]]) -> 150000 | O85: =IF(old_data[[#This Row],[Net Revenue (₦)]]>350000,"High",IF(old_data[[#This Row],[Net Revenue (₦)]]>100000,"Medium","Low")) -> Medium
... A90: ORD-1089 | B90: PKG-009 | C90: CrispBite Corn Chips 100g | D90: Snacks | E90: West | F90: Convenience Store | G90: Fatima Musa | H90: 45383 | I90: 179 | J90: 280 | K90: 0 | L90: Paid | M90: =old_data[[#This Row],[Units Sold]]*old_data[[#This Row],[Unit Price (₦)]] -> 50120 | N90: =old_data[[#This Row],[Total Sales (₦)]]*(1-old_data[[#This Row],[Discount (%)]]) -> 50120 | O90: =IF(old_data[[#This Row],[Net Revenue (₦)]]>350000,"High",IF(old_data[[#This Row],[Net Revenue (₦)]]>100000,"Medium","Low")) -> Low
A91: ORD-1090 | B91: PKG-010 | C91: GoldenBite Chocolate Cookies 150g | D91: Baked Goods | E91: Central | F91: Pharmacy | G91: Chidi Nwosu | H91: 45384 | I91: 111 | J91: 750 | K91: 0 | L91: Pending | M91: 83250 | N91: =old_data[[#This Row],[Total Sales (₦)]]*(1-old_data[[#This Row],[Discount (%)]]) -> 83250 | O91: =IF(old_data[[#This Row],[Net Revenue (₦)]]>350000,"High",IF(old_data[[#This Row],[Net Revenue (₦)]]>100000,"Medium","Low")) -> Low
A92: ORD-1091 | B92: PKG-001 | C92: FreshSip Orange Juice 1L | D92: Beverages | E92: North | F92: Supermarket | G92: Amara Osei | H92: 45385 | I92: 258 | J92: 990 | K92: 0.04 | L92: Paid | M92: =old_data[[#This Row],[Units Sold]]*old_data[[#This Row],[Unit Price (₦)]] -> 255420 | N92: =old_data[[#This Row],[Total Sales (₦)]]*(1-old_data[[#This Row],[Discount (%)]]) -> 245203.2 | O92: =IF(old_data[[#This Row],[Net Revenue (₦)]]>350000,"High",IF(old_data[[#This Row],[Net Revenue (₦)]]>100000,"Medium","Low")) -> Medium
A93: ORD-1092 | B93: PKG-002 | C93: NutriMix Granola Bar | D93: Snacks | E93: South | F93: Wholesaler | G93: Tunde Bello | H93: 45386 | I93: 488 | J93: 350 | K93: 0 | L93: Pending | M93: =old_data[[#This Row],[Units Sold]]*old_data[[#This Row],[Unit Price (₦)]] -> 170800 | N93: =old_data[[#This Row],[Total Sales (₦)]]*(1-old_data[[#This Row],[Discount (%)]]) -> 170800 | O93: =IF(old_data[[#This Row],[Net Revenue (₦)]]>350000,"High",IF(old_data[[#This Row],[Net Revenue (₦)]]>100000,"Medium","Low")) -> Medium
A94: ORD-1093 | B94: PKG-003 | C94: CrispBite Potato Chips 150g | D94: Snacks | E94: East | F94: Online | G94: Ngozi Eze | H94: 45387 | I94: 305 | J94: 420 | K94: 0 | L94: Paid | M94: =old_data[[#This Row],[Units Sold]]*old_data[[#This Row],[Unit Price (₦)]] -> 128100 | N94: =old_data[[#This Row],[Total Sales (₦)]]*(1-old_data[[#This Row],[Discount (%)]]) -> 128100 | O94: =IF(old_data[[#This Row],[Net Revenue (₦)]]>350000,"High",IF(old_data[[#This Row],[Net Revenue (₦)]]>100000,"Medium","Low")) -> Medium
A95: ORD-1094 | B95: PKG-004 | C95: DailyBrew Green Tea 25 bags | D95: Beverages | E95: West | F95: Convenience Store | G95: Emeka Okafor | H95: 45388 | I95: 411 | J95: 1200 | K95: 0.07 | L95: Paid | M95: =old_data[[#This Row],[Units Sold]]*old_data[[#This Row],[Unit Price (₦)]] -> 493200 | N95: =old_data[[#This Row],[Total Sales (₦)]]*(1-old_data[[#This Row],[Discount (%)]]) -> 458676 | O95: =IF(old_data[[#This Row],[Net Revenue (₦)]]>350000,"High",IF(old_data[[#This Row],[Net Revenue (₦)]]>100000,"Medium","Low")) -> High
A96: ORD-1095 | B96: PKG-005 | C96: HealthPure Bottled Water 500ml | D96: Beverages | E96: Central | F96: Pharmacy | G96: Fatima Musa | H96: 45389 | I96: 58 | J96: 200 | K96: 0 | L96: Pending | M96: =old_data[[#This Row],[Units Sold]]*old_data[[#This Row],[Unit Price (₦)]] -> 11600 | N96: =old_data[[#This Row],[Total Sales (₦)]]*(1-old_data[[#This Row],[Discount (%)]]) -> 11600 | O96: =IF(old_data[[#This Row],[Net Revenue (₦)]]>350000,"High",IF(old_data[[#This Row],[Net Revenue (₦)]]>100000,"Medium","Low")) -> Low
A97: ORD-1096 | B97: PKG-006 | C97: GoldenBite Biscuits 200g | D97: Baked Goods | E97: North | F97: Supermarket | G97: Chidi Nwosu | H97: 45390 | I97: 230 | J97: 895 | K97: 0 | L97: Paid | M97: =old_data[[#This Row],[Units Sold]]*old_data[[#This Row],[Unit Price (₦)]] -> 205850 | N97: =old_data[[#This Row],[Total Sales (₦)]]*(1-old_data[[#This Row],[Discount (%)]]) -> 205850 | O97: =IF(old_data[[#This Row],[Net Revenue (₦)]]>350000,"High",IF(old_data[[#This Row],[Net Revenue (₦)]]>100000,"Medium","Low")) -> Medium
A98: ORD-1097 | B98: PKG-007 | C98: FreshSip Mango Juice 500ml | D98: Beverages | E98: South | F98: Wholesaler | G98: Amara Osei | H98: 45391 | I98: 220 | J98: 650 | K98: 0.11 | L98: Pending | M98: =old_data[[#This Row],[Units Sold]]*old_data[[#This Row],[Unit Price (₦)]] -> 143000 | N98: =old_data[[#This Row],[Total Sales (₦)]]*(1-old_data[[#This Row],[Discount (%)]]) -> 127270 | O98: =IF(old_data[[#This Row],[Net Revenue (₦)]]>350000,"High",IF(old_data[[#This Row],[Net Revenue (₦)]]>100000,"Medium","Low")) -> Medium
A99: ORD-1098 | B99: PKG-008 | C99: NutriMix Cereal Box 500g | D99: Breakfast | E99: East | F99: Online | G99: Tunde Bello | H99: 45392 | I99: 354 | J99: 2800 | K99: 0 | L99: Paid | M99: =old_data[[#This Row],[Units Sold]]*old_data[[#This Row],[Unit Price (₦)]] -> 991200 | N99: =old_data[[#This Row],[Total Sales (₦)]]*(1-old_data[[#This Row],[Discount (%)]]) -> 991200 | O99: =IF(old_data[[#This Row],[Net Revenue (₦)]]>350000,"High",IF(old_data[[#This Row],[Net Revenue (₦)]]>100000,"Medium","Low")) -> High
A100: ORD-1099 | B100: PKG-009 | C100: CrispBite Corn Chips 100g | D100: Snacks | E100: West | F100: Convenience Store | G100: Ngozi Eze | H100: 45393 | I100: 340 | J100: 280 | K100: 0 | L100: Paid | M100: =old_data[[#This Row],[Units Sold]]*old_data[[#This Row],[Unit Price (₦)]] -> 95200 | N100: =old_data[[#This Row],[Total Sales (₦)]]*(1-old_data[[#This Row],[Discount (%)]]) -> 95200 | O100: =IF(old_data[[#This Row],[Net Revenue (₦)]]>350000,"High",IF(old_data[[#This Row],[Net Revenue (₦)]]>100000,"Medium","Low")) -> Low
A101: ORD-1100 | B101: PKG-010 | C101: GoldenBite Chocolate Cookies 150g | D101: Baked Goods | E101: Central | F101: Pharmacy | G101: Emeka Okafor | H101: 45394 | I101: 216 | J101: 750 | K101: 0.12 | L101: Pending | M101: =old_data[[#This Row],[Units Sold]]*old_data[[#This Row],[Unit Price (₦)]] -> 162000 | N101: =old_data[[#This Row],[Total Sales (₦)]]*(1-old_data[[#This Row],[Discount (%)]]) -> 142560 | O101: =IF(old_data[[#This Row],[Net Revenue (₦)]]>350000,"High",IF(old_data[[#This Row],[Net Revenue (₦)]]>100000,"Medium","Low")) -> Medium
A102: ORD-1101 | B102: PKG-001 | C102: FreshSip Orange Juice 1L | D102: Beverages | E102: North | F102: Supermarket | G102: Fatima Musa | H102: 45395 | I102: 65 | J102: 990 | K102: 0 | L102: Paid | M102: =old_data[[#This Row],[Units Sold]]*old_data[[#This Row],[Unit Price (₦)]] -> 64350 | N102: =old_data[[#This Row],[Total Sales (₦)]]*(1-old_data[[#This Row],[Discount (%)]]) -> 64350 | O102: =IF(old_data[[#This Row],[Net Revenue (₦)]]>350000,"High",IF(old_data[[#This Row],[Net Revenue (₦)]]>100000,"Medium","Low")) -> Low
A103: ORD-1102 | B103: PKG-002 | C103: NutriMix Granola Bar | D103: Snacks | E103: South | F103: Wholesaler | G103: Chidi Nwosu | H103: 45396 | I103: 107 | J103: 350 | K103: 0 | L103: Pending | M103: =old_data[[#This Row],[Units Sold]]*old_data[[#This Row],[Unit Price (₦)]] -> 37450 | N103: =old_data[[#This Row],[Total Sales (₦)]]*(1-old_data[[#This Row],[Discount (%)]]) -> 37450 | O103: =IF(old_data[[#This Row],[Net Revenue (₦)]]>350000,"High",IF(old_data[[#This Row],[Net Revenue (₦)]]>100000,"Medium","Low")) -> Low
A104: ORD-1103 | B104: PKG-003 | C104: CrispBite Potato Chips 150g | D104: Snacks | E104: East | F104: Online | G104: Amara Osei | H104: 45397 | I104: 81 | J104: 420 | K104: 0.06 | L104: Paid | M104: =old_data[[#This Row],[Units Sold]]*old_data[[#This Row],[Unit Price (₦)]] -> 34020 | N104: =old_data[[#This Row],[Total Sales (₦)]]*(1-old_data[[#This Row],[Discount (%)]]) -> 31978.8 | O104: =IF(old_data[[#This Row],[Net Revenue (₦)]]>350000,"High",IF(old_data[[#This Row],[Net Revenue (₦)]]>100000,"Medium","Low")) -> Low
A105: ORD-1104 | B105: PKG-004 | C105: DailyBrew Green Tea 25 bags | D105: Beverages | E105: West | F105: Convenience Store | G105: Tunde Bello | H105: 45398 | I105: 100 | J105: 1200 | K105: 0 | L105: Paid | M105: 120000 | N105: =old_data[[#This Row],[Total Sales (₦)]]*(1-old_data[[#This Row],[Discount (%)]]) -> 120000 | O105: =IF(old_data[[#This Row],[Net Revenue (₦)]]>350000,"High",IF(old_data[[#This Row],[Net Revenue (₦)]]>100000,"Medium","Low")) -> Medium
A106: ORD-1105 | B106: PKG-005 | C106: HealthPure Bottled Water 500ml | D106: Beverages | E106: Central | F106: Pharmacy | G106: Ngozi Eze | H106: 45399 | I106: 48 | J106: 200 | K106: 0 | L106: Pending | M106: =old_data[[#This Row],[Units Sold]]*old_data[[#This Row],[Unit Price (₦)]] -> 9600 | N106: =old_data[[#This Row],[Total Sales (₦)]]*(1-old_data[[#This Row],[Discount (%)]]) -> 9600 | O106: =IF(old_data[[#This Row],[Net Revenue (₦)]]>350000,"High",IF(old_data[[#This Row],[Net Revenue (₦)]]>100000,"Medium","Low")) -> Low
A107: ORD-1106 | B107: PKG-006 | C107: GoldenBite Biscuits 200g | D107: Baked Goods | E107: North | F107: Supermarket | G107: Emeka Okafor | H107: 45400 | I107: 451 | J107: 895 | K107: 0.03 | L107: Paid | M107: =old_data[[#This Row],[Units Sold]]*old_data[[#This Row],[Unit Price (₦)]] -> 403645 | N107: =old_data[[#This Row],[Total Sales (₦)]]*(1-old_data[[#This Row],[Discount (%)]]) -> 391535.65 | O107: =IF(old_data[[#This Row],[Net Revenue (₦)]]>350000,"High",IF(old_data[[#This Row],[Net Revenue (₦)]]>100000,"Medium","Low")) -> High
A108: ORD-1107 | B108: PKG-007 | C108: FreshSip Mango Juice 500ml | D108: Beverages | E108: South | F108: Wholesaler | G108: Fatima Musa | H108: 45401 | I108: 343 | J108: 650 | K108: 0 | L108: Pending | M108: =old_data[[#This Row],[Units Sold]]*old_data[[#This Row],[Unit Price (₦)]] -> 222950 | N108: =old_data[[#This Row],[Total Sales (₦)]]*(1-old_data[[#This Row],[Discount (%)]]) -> 222950 | O108: =IF(old_data[[#This Row],[Net Revenue (₦)]]>350000,"High",IF(old_data[[#This Row],[Net Revenue (₦)]]>100000,"Medium","Low")) -> Medium
A109: ORD-1108 | B109: PKG-008 | C109: NutriMix Cereal Box 500g | D109: Breakfast | E109: East | F109: Online | G109: Chidi Nwosu | H109: 45402 | I109: 438 | J109: 2800 | K109: 0 | L109: Paid | M109: =old_data[[#This Row],[Units Sold]]*old_data[[#This Row],[Unit Price (₦)]] -> 1226400 | N109: =old_data[[#This Row],[Total Sales (₦)]]*(1-old_data[[#This Row],[Discount (%)]]) -> 1226400 | O109: =IF(old_data[[#This Row],[Net Revenue (₦)]]>350000,"High",IF(old_data[[#This Row],[Net Revenue (₦)]]>100000,"Medium","Low")) -> High
A110: ORD-1109 | B110: PKG-009 | C110: CrispBite Corn Chips 100g | D110: Snacks | E110: West | F110: Convenience Store | G110: Amara Osei | H110: 45403 | I110: 57 | J110: 280 | K110: 0.13 | L110: Paid | M110: =old_data[[#This Row],[Units Sold]]*old_data[[#This Row],[Unit Price (₦)]] -> 15960 | N110: =old_data[[#This Row],[Total Sales (₦)]]*(1-old_data[[#This Row],[Discount (%)]]) -> 13885.2 | O110: =IF(old_data[[#This Row],[Net Revenue (₦)]]>350000,"High",IF(old_data[[#This Row],[Net Revenue (₦)]]>100000,"Medium","Low")) -> Low
A111: ORD-1110 | B111: PKG-010 | C111: GoldenBite Chocolate Cookies 150g | D111: Baked Goods | E111: Central | F111: Pharmacy | G111: Tunde Bello | H111: 45404 | I111: 95 | J111: 750 | K111: 0 | L111: Pending | M111: =old_data[[#This Row],[Units Sold]]*old_data[[#This Row],[Unit Price (₦)]] -> 71250 | N111: =old_data[[#This Row],[Total Sales (₦)]]*(1-old_data[[#This Row],[Discount (%)]]) -> 71250 | O111: =IF(old_data[[#This Row],[Net Revenue (₦)]]>350000,"High",IF(old_data[[#This Row],[Net Revenue (₦)]]>100000,"Medium","Low")) -> Low
A112: ORD-1111 | B112: PKG-001 | C112: FreshSip Orange Juice 1L | D112: Beverages | E112: North | F112: Supermarket | G112: Ngozi Eze | H112: 45405 | I112: 256 | J112: 990 | K112: 0 | L112: Paid | M112: =old_data[[#This Row],[Units Sold]]*old_data[[#This Row],[Unit Price (₦)]] -> 253440 | N112: =old_data[[#This Row],[Total Sales (₦)]]*(1-old_data[[#This Row],[Discount (%)]]) -> 253440 | O112: =IF(old_data[[#This Row],[Net Revenue (₦)]]>350000,"High",IF(old_data[[#This Row],[Net Revenue (₦)]]>100000,"Medium","Low")) -> Medium
A113: ORD-1112 | B113: PKG-002 | C113: NutriMix Granola Bar | D113: Snacks | E113: South | F113: Wholesaler | G113: Emeka Okafor | H113: 45406 | I113: 215 | J113: 350 | K113: 0.04 | L113: Pending | M113: =old_data[[#This Row],[Units Sold]]*old_data[[#This Row],[Unit Price (₦)]] -> 75250 | N113: =old_data[[#This Row],[Total Sales (₦)]]*(1-old_data[[#This Row],[Discount (%)]]) -> 72240 | O113: =IF(old_data[[#This Row],[Net Revenue (₦)]]>350000,"High",IF(old_data[[#This Row],[Net Revenue (₦)]]>100000,"Medium","Low")) -> Low
A114: ORD-1113 | B114: PKG-003 | C114: CrispBite Potato Chips 150g | D114: Snacks | E114: East | F114: Online | G114: Fatima Musa | H114: 45407 | I114: 160 | J114: 420 | K114: 0 | L114: Paid | M114: 67200 | N114: =old_data[[#This Row],[Total Sales (₦)]]*(1-old_data[[#This Row],[Discount (%)]]) -> 67200 | O114: =IF(old_data[[#This Row],[Net Revenue (₦)]]>350000,"High",IF(old_data[[#This Row],[Net Revenue (₦)]]>100000,"Medium","Low")) -> Low
...

Sheet New_Sales_Data
A1: Order ID | B1: Product ID | C1: Product Name | D1: Category | E1: Region | F1: Sales Channel | G1: Sales Rep | H1: Order Date | I1: Units Sold | J1: Unit Price (₦) | K1: Discount (%) | L1: Payment Status | M1: Total Sales (₦) | N1: Net Revenue (₦) | O1: Revenue Tier
A2: ORD-1500 | B2: PKG-003 | C2: CrispBite Potato Chips 150g | D2: Snacks | E2: East | F2: Supermarket | G2: Chidi Nwosu | H2: 45450 | I2: 77 | J2: 420 | K2: 0.05 | L2: Pending | M2: 32340 | N2: 30723 | O2: Low
A3: ORD-1501 | B3: PKG-008 | C3: NutriMix Cereal Box 500g | D3: Breakfast | E3: Central | F3: Convenience Store | G3: Emeka Okafor | H3: 45473 | I3: 74 | J3: 2800 | K3: 0.08 | L3: Pending | M3: 207200 | N3: 190624 | O3: Medium
A4: ORD-1502 | B4: PKG-009 | C4: CrispBite Corn Chips 100g | D4: Snacks | E4: North | F4: Online | G4: Amara Osei | H4: 45457 | I4: 99 | J4: 280 | K4: 0.11 | L4: Paid | M4: 27720 | N4: 24670.8 | O4: Low
A5: ORD-1503 | B5: PKG-008 | C5: NutriMix Cereal Box 500g | D5: Breakfast | E5: South | F5: Supermarket | G5: Emeka Okafor | H5: 45462 | I5: 39 | J5: 2800 | K5: 0 | L5: Paid | M5: 109200 | N5: 109200 | O5: Medium
A6: ORD-1504 | B6: PKG-007 | C6: FreshSip Mango Juice 500ml | D6: Beverages | E6: South | F6: Wholesaler | G6: Tunde Bello | H6: 45467 | I6: 135 | J6: 650 | K6: 0 | L6: Pending | M6: 87750 | N6: 87750 | O6: Low
A7: ORD-1505 | B7: PKG-001 | C7: FreshSip Orange Juice 1L | D7: Beverages | E7: North | F7: Convenience Store | G7: Ngozi Eze | H7: 45470 | I7: 103 | J7: 990 | K7: 0.07 | L7: Paid | M7: 101970 | N7: 94832.1 | O7: Low
A8: ORD-1506 | B8: PKG-008 | C8: NutriMix Cereal Box 500g | D8: Breakfast | E8: South | F8: Wholesaler | G8: Tunde Bello | H8: 45451 | I8: 49 | J8: 2800 | K8: 0.11 | L8: Pending | M8: 137200 | N8: 122108 | O8: Medium
A9: ORD-1507 | B9: PKG-005 | C9: HealthPure Bottled Water 500ml | D9: Beverages | E9: South | F9: Convenience Store | G9: Emeka Okafor | H9: 45450 | I9: 189 | J9: 200 | K9: 0.12 | L9: Paid | M9: 37800 | N9: 33264 | O9: Low
A10: ORD-1508 | B10: PKG-002 | C10: NutriMix Granola Bar | D10: Snacks | E10: East | F10: Supermarket | G10: Chidi Nwosu | H10: 45456 | I10: 96 | J10: 350 | K10: 0.05 | L10: Pending | M10: 33600 | N10: 31920 | O10: Low
A11: ORD-1509 | B11: PKG-002 | C11: NutriMix Granola Bar | D11: Snacks | E11: Central | F11: Convenience Store | G11: Emeka Okafor | H11: 45448 | I11: 157 | J11: 350 | K11: 0.1 | L11: Pending | M11: 54950 | N11: 49455 | O11: Low
A12: ORD-1510 | B12: PKG-009 | C12: CrispBite Corn Chips 100g | D12: Snacks | E12: East | F12: Supermarket | G12: Ngozi Eze | H12: 45452 | I12: 97 | J12: 280 | K12: 0.08 | L12: Paid | M12: 27160 | N12: 24987.2 | O12: Low
A13: ORD-1511 | B13: PKG-010 | C13: GoldenBite Chocolate Cookies 150g | D13: Baked Goods | E13: South | F13: Online | G13: Amara Osei | H13: 45459 | I13: 80 | J13: 750 | K13: 0.15 | L13: Paid | M13: 60000 | N13: 51000 | O13: Low
... A1297: ORD-2795 | B1297: PKG-007 | C1297: FreshSip Mango Juice 500ml | D1297: Beverages | E1297: North | F1297: Online | G1297: Tunde Bello | H1297: 46157 | I1297: 235 | J1297: 650 | K1297: 0.08 | L1297: Paid | M1297: 152750 | N1297: 140530 | O1297: Medium

Sheet Combined_Data
A1: Order ID | B1: Product ID | C1: Product Name | D1: Category | E1: Region | F1: Sales Channel | G1: Sales Rep | H1: Order Date | I1: Units Sold | J1: Unit Price (₦) | K1: Discount (%) | L1: Payment Status | M1: Total Sales (₦) | N1: Net Revenue (₦) | O1: Revenue Tier
A2: ORD-1001 | B2: PKG-001 | C2: FreshSip Orange Juice 1L | D2: Beverages | E2: North | F2: Supermarket | G2: Amara Osei | H2: 45292 | I2: 337 | J2: 990 | K2: 0.12 | L2: Paid | M2: =Combined_Data!$I2*Combined_Data!$J2 -> 333630 | N2: =Combined_Data!$M2*(1-Combined_Data!$K2) -> 293594.4 | O2: =IF(Combined_Data!$N2>350000,"High",IF(Combined_Data!$N2>100000,"Medium","Low")) -> Medium
A3: ORD-1002 | B3: PKG-002 | C3: NutriMix Granola Bar | D3: Snacks | E3: South | F3: Wholesaler | G3: Tunde Bello | H3: 45293 | I3: 135 | J3: 350 | K3: 0 | L3: Pending | M3: =Combined_Data!$I3*Combined_Data!$J3 -> 47250 | N3: =Combined_Data!$M3*(1-Combined_Data!$K3) -> 47250 | O3: =IF(Combined_Data!$N3>350000,"High",IF(Combined_Data!$N3>100000,"Medium","Low")) -> Low
A4: ORD-1003 | B4: PKG-003 | C4: CrispBite Potato Chips 150g | D4: Snacks | E4: East | F4: Online | G4: Ngozi Eze | H4: 45294 | I4: 387 | J4: 420 | K4: 0 | L4: Paid | M4: =Combined_Data!$I4*Combined_Data!$J4 -> 162540 | N4: =Combined_Data!$M4*(1-Combined_Data!$K4) -> 162540 | O4: =IF(Combined_Data!$N4>350000,"High",IF(Combined_Data!$N4>100000,"Medium","Low")) -> Medium
A5: ORD-1004 | B5: PKG-004 | C5: DailyBrew Green Tea 25 bags | D5: Beverages | E5: West | F5: Convenience Store | G5: Emeka Okafor | H5: 45295 | I5: 389 | J5: 1200 | K5: 0.03 | L5: Paid | M5: =Combined_Data!$I5*Combined_Data!$J5 -> 466800 | N5: =Combined_Data!$M5*(1-Combined_Data!$K5) -> 452796 | O5: =IF(Combined_Data!$N5>350000,"High",IF(Combined_Data!$N5>100000,"Medium","Low")) -> High
A6: ORD-1005 | B6: PKG-005 | C6: HealthPure Bottled Water 500ml | D6: Beverages | E6: Central | F6: Pharmacy | G6: Fatima Musa | H6: 45296 | I6: 226 | J6: 200 | K6: 0 | L6: Pending | M6: =Combined_Data!$I6*Combined_Data!$J6 -> 45200 | N6: =Combined_Data!$M6*(1-Combined_Data!$K6) -> 45200 | O6: =IF(Combined_Data!$N6>350000,"High",IF(Combined_Data!$N6>100000,"Medium","Low")) -> Low
A7: ORD-1006 | B7: PKG-006 | C7: GoldenBite Biscuits 200g | D7: Baked Goods | E7: North | F7: Supermarket | G7: Chidi Nwosu | H7: 45297 | I7: 100 | J7: 895 | K7: 0 | L7: Paid | M7: 89500 | N7: =Combined_Data!$M7*(1-Combined_Data!$K7) -> 89500 | O7: =IF(Combined_Data!$N7>350000,"High",IF(Combined_Data!$N7>100000,"Medium","Low")) -> Low
A8: ORD-1007 | B8: PKG-007 | C8: FreshSip Mango Juice 500ml | D8: Beverages | E8: South | F8: Wholesaler | G8: Amara Osei | H8: 45298 | I8: 268 | J8: 650 | K8: 0.09 | L8: Pending | M8: =Combined_Data!$I8*Combined_Data!$J8 -> 174200 | N8: =Combined_Data!$M8*(1-Combined_Data!$K8) -> 158522 | O8: =IF(Combined_Data!$N8>350000,"High",IF(Combined_Data!$N8>100000,"Medium","Low")) -> Medium
A9: ORD-1008 | B9: PKG-008 | C9: NutriMix Cereal Box 500g | D9: Breakfast | E9: East | F9: Online | G9: Tunde Bello | H9: 45299 | I9: 376 | J9: 2800 | K9: 0 | L9: Paid | M9: =Combined_Data!$I9*Combined_Data!$J9 -> 1052800 | N9: =Combined_Data!$M9*(1-Combined_Data!$K9) -> 1052800 | O9: =IF(Combined_Data!$N9>350000,"High",IF(Combined_Data!$N9>100000,"Medium","Low")) -> High
A10: ORD-1009 | B10: PKG-009 | C10: CrispBite Corn Chips 100g | D10: Snacks | E10: West | F10: Convenience Store | G10: Ngozi Eze | H10: 45300 | I10: 289 | J10: 280 | K10: 0 | L10: Paid | M10: =Combined_Data!$I10*Combined_Data!$J10 -> 80920 | N10: =Combined_Data!$M10*(1-Combined_Data!$K10) -> 80920 | O10: =IF(Combined_Data!$N10>350000,"High",IF(Combined_Data!$N10>100000,"Medium","Low")) -> Low
A11: ORD-1010 | B11: PKG-010 | C11: GoldenBite Chocolate Cookies 150g | D11: Baked Goods | E11: Central | F11: Pharmacy | G11: Emeka Okafor | H11: 45301 | I11: 239 | J11: 750 | K11: 0.13 | L11: Pending | M11: =Combined_Data!$I11*Combined_Data!$J11 -> 179250 | N11: =Combined_Data!$M11*(1-Combined_Data!$K11) -> 155947.5 | O11: =IF(Combined_Data!$N11>350000,"High",IF(Combined_Data!$N11>100000,"Medium","Low")) -> Medium
A12: ORD-1011 | B12: PKG-001 | C12: FreshSip Orange Juice 1L | D12: Beverages | E12: North | F12: Supermarket | G12: Fatima Musa | H12: 45302 | I12: 13 | J12: 990 | K12: 0 | L12: Paid | M12: =Combined_Data!$I12*Combined_Data!$J12 -> 12870 | N12: =Combined_Data!$M12*(1-Combined_Data!$K12) -> 12870 | O12: =IF(Combined_Data!$N12>350000,"High",IF(Combined_Data!$N12>100000,"Medium","Low")) -> Low
A13: ORD-1012 | B13: PKG-002 | C13: NutriMix Granola Bar | D13: Snacks | E13: South | F13: Wholesaler | G13: Chidi Nwosu | H13: 45304 | I13: 91 | J13: 350 | K13: 0 | L13: Pending | M13: =Combined_Data!$I13*Combined_Data!$J13 -> 31850 | N13: =Combined_Data!$M13*(1-Combined_Data!$K13) -> 31850 | O13: =IF(Combined_Data!$N13>350000,"High",IF(Combined_Data!$N13>100000,"Medium","Low")) -> Low
A14: ORD-1013 | B14: PKG-003 | C14: CrispBite Potato Chips 150g | D14: Snacks | E14: East | F14: Online | G14: Amara Osei | H14: 45305 | I14: 184 | J14: 420 | K14: 0.05 | L14: Paid | M14: =Combined_Data!$I14*Combined_Data!$J14 -> 77280 | N14: =Combined_Data!$M14*(1-Combined_Data!$K14) -> 73416 | O14: =IF(Combined_Data!$N14>350000,"High",IF(Combined_Data!$N14>100000,"Medium","Low")) -> Low
A15: ORD-1014 | B15: PKG-004 | C15: DailyBrew Green Tea 25 bags | D15: Beverages | E15: West | F15: Convenience Store | G15: Tunde Bello | H15: 45306 | I15: 400 | J15: 1200 | K15: 0 | L15: Paid | M15: =Combined_Data!$I15*Combined_Data!$J15 -> 480000 | N15: =Combined_Data!$M15*(1-Combined_Data!$K15) -> 480000 | O15: =IF(Combined_Data!$N15>350000,"High",IF(Combined_Data!$N15>100000,"Medium","Low")) -> High
A16: ORD-1015 | B16: PKG-005 | C16: HealthPure Bottled Water 500ml | D16: Beverages | E16: Central | F16: Pharmacy | G16: Ngozi Eze | H16: 45307 | I16: 57 | J16: 200 | K16: 0 | L16: Pending | M16: =Combined_Data!$I16*Combined_Data!$J16 -> 11400 | N16: =Combined_Data!$M16*(1-Combined_Data!$K16) -> 11400 | O16: =IF(Combined_Data!$N16>350000,"High",IF(Combined_Data!$N16>100000,"Medium","Low")) -> Low
A17: ORD-1016 | B17: PKG-006 | C17: GoldenBite Biscuits 200g | D17: Baked Goods | E17: North | F17: Supermarket | G17: Emeka Okafor | H17: 45308 | I17: 193 | J17: 895 | K17: 0.1 | L17: Paid | M17: =Combined_Data!$I17*Combined_Data!$J17 -> 172735 | N17: =Combined_Data!$M17*(1-Combined_Data!$K17) -> 155461.5 | O17: =IF(Combined_Data!$N17>350000,"High",IF(Combined_Data!$N17>100000,"Medium","Low")) -> Medium
A18: ORD-1017 | B18: PKG-007 | C18: FreshSip Mango Juice 500ml | D18: Beverages | E18: South | F18: Wholesaler | G18: Fatima Musa | H18: 45309 | I18: 423 | J18: 650 | K18: 0 | L18: Pending | M18: =Combined_Data!$I18*Combined_Data!$J18 -> 274950 | N18: =Combined_Data!$M18*(1-Combined_Data!$K18) -> 274950 | O18: =IF(Combined_Data!$N18>350000,"High",IF(Combined_Data!$N18>100000,"Medium","Low")) -> Medium
A19: ORD-1018 | B19: PKG-008 | C19: NutriMix Cereal Box 500g | D19: Breakfast | E19: East | F19: Online | G19: Chidi Nwosu | H19: 45310 | I19: 245 | J19: 2800 | K19: 0 | L19: Paid | M19: =Combined_Data!$I19*Combined_Data!$J19 -> 686000 | N19: =Combined_Data!$M19*(1-Combined_Data!$K19) -> 686000 | O19: =IF(Combined_Data!$N19>350000,"High",IF(Combined_Data!$N19>100000,"Medium","Low")) -> High
... A23: ORD-1022 | B23: PKG-002 | C23: NutriMix Granola Bar | D23: Snacks | E23: South | F23: Wholesaler | G23: Emeka Okafor | H23: 45314 | I23: 305 | J23: 350 | K23: 0.03 | L23: Pending | M23: =Combined_Data!$I23*Combined_Data!$J23 -> 106750 | N23: =Combined_Data!$M23*(1-Combined_Data!$K23) -> 103547.5 | O23: =IF(Combined_Data!$N23>350000,"High",IF(Combined_Data!$N23>100000,"Medium","Low")) -> Medium
A24: ORD-1023 | B24: PKG-003 | C24: CrispBite Potato Chips 150g | D24: Snacks | E24: East | F24: Online | G24: Fatima Musa | H24: 45315 | I24: 150 | J24: 420 | K24: 0 | L24: Paid | M24: 63000 | N24: =Combined_Data!$M24*(1-Combined_Data!$K24) -> 63000 | O24: =IF(Combined_Data!$N24>350000,"High",IF(Combined_Data!$N24>100000,"Medium","Low")) -> Low
A25: ORD-1024 | B25: PKG-004 | C25: DailyBrew Green Tea 25 bags | D25: Beverages | E25: West | F25: Convenience Store | G25: Chidi Nwosu | H25: 45316 | I25: 158 | J25: 1200 | K25: 0 | L25: Paid | M25: =Combined_Data!$I25*Combined_Data!$J25 -> 189600 | N25: =Combined_Data!$M25*(1-Combined_Data!$K25) -> 189600 | O25: =IF(Combined_Data!$N25>350000,"High",IF(Combined_Data!$N25>100000,"Medium","Low")) -> Medium
A26: ORD-1025 | B26: PKG-005 | C26: HealthPure Bottled Water 500ml | D26: Beverages | E26: Central | F26: Pharmacy | G26: Amara Osei | H26: 45317 | I26: 447 | J26: 200 | K26: 0.03 | L26: Pending | M26: =Combined_Data!$I26*Combined_Data!$J26 -> 89400 | N26: =Combined_Data!$M26*(1-Combined_Data!$K26) -> 86718 | O26: =IF(Combined_Data!$N26>350000,"High",IF(Combined_Data!$N26>100000,"Medium","Low")) -> Low
A27: ORD-1026 | B27: PKG-006 | C27: GoldenBite Biscuits 200g | D27: Baked Goods | E27: North | F27: Supermarket | G27: Tunde Bello | H27: 45318 | I27: 152 | J27: 895 | K27: 0 | L27: Paid | M27: =Combined_Data!$I27*Combined_Data!$J27 -> 136040 | N27: =Combined_Data!$M27*(1-Combined_Data!$K27) -> 136040 | O27: =IF(Combined_Data!$N27>350000,"High",IF(Combined_Data!$N27>100000,"Medium","Low")) -> Medium
A28: ORD-1027 | B28: PKG-007 | C28: FreshSip Mango Juice 500ml | D28: Beverages | E28: South | F28: Wholesaler | G28: Ngozi Eze | H28: 45319 | I28: 437 | J28: 650 | K28: 0 | L28: Pending | M28: =Combined_Data!$I28*Combined_Data!$J28 -> 284050 | N28: =Combined_Data!$M28*(1-Combined_Data!$K28) -> 284050 | O28: =IF(Combined_Data!$N28>350000,"High",IF(Combined_Data!$N28>100000,"Medium","Low")) -> Medium
A29: ORD-1028 | B29: PKG-008 | C29: NutriMix Cereal Box 500g | D29: Breakfast | E29: East | F29: Online | G29: Emeka Okafor | H29: 45320 | I29: 199 | J29: 2800 | K29: 0.11 | L29: Paid | M29: =Combined_Data!$I29*Combined_Data!$J29 -> 557200 | N29: =Combined_Data!$M29*(1-Combined_Data!$K29) -> 495908 | O29: =IF(Combined_Data!$N29>350000,"High",IF(Combined_Data!$N29>100000,"Medium","Low")) -> High
A30: ORD-1029 | B30: PKG-009 | C30: CrispBite Corn Chips 100g | D30: Snacks | E30: West | F30: Convenience Store | G30: Fatima Musa | H30: 45321 | I30: 369 | J30: 280 | K30: 0 | L30: Paid | M30: =Combined_Data!$I30*Combined_Data!$J30 -> 103320 | N30: =Combined_Data!$M30*(1-Combined_Data!$K30) -> 103320 | O30: =IF(Combined_Data!$N30>350000,"High",IF(Combined_Data!$N30>100000,"Medium","Low")) -> Medium
A31: ORD-1030 | B31: PKG-010 | C31: GoldenBite Chocolate Cookies 150g | D31: Baked Goods | E31: Central | F31: Pharmacy | G31: Chidi Nwosu | H31: 45322 | I31: 341 | J31: 750 | K31: 0 | L31: Pending | M31: =Combined_Data!$I31*Combined_Data!$J31 -> 255750 | N31: =Combined_Data!$M31*(1-Combined_Data!$K31) -> 255750 | O31: =IF(Combined_Data!$N31>350000,"High",IF(Combined_Data!$N31>100000,"Medium","Low")) -> Medium
A32: ORD-1031 | B32: PKG-001 | C32: FreshSip Orange Juice 1L | D32: Beverages | E32: North | F32: Supermarket | G32: Amara Osei | H32: 45323 | I32: 335 | J32: 990 | K32: 0.11 | L32: Paid | M32: =Combined_Data!$I32*Combined_Data!$J32 -> 331650 | N32: =Combined_Data!$M32*(1-Combined_Data!$K32) -> 295168.5 | O32: =IF(Combined_Data!$N32>350000,"High",IF(Combined_Data!$N32>100000,"Medium","Low")) -> Medium
A33: ORD-1032 | B33: PKG-002 | C33: NutriMix Granola Bar | D33: Snacks | E33: South | F33: Wholesaler | G33: Tunde Bello | H33: 45324 | I33: 93 | J33: 350 | K33: 0 | L33: Pending | M33: =Combined_Data!$I33*Combined_Data!$J33 -> 32550 | N33: =Combined_Data!$M33*(1-Combined_Data!$K33) -> 32550 | O33: =IF(Combined_Data!$N33>350000,"High",IF(Combined_Data!$N33>100000,"Medium","Low")) -> Low
A34: ORD-1033 | B34: PKG-003 | C34: CrispBite Potato Chips 150g | D34: Snacks | E34: East | F34: Online | G34: Ngozi Eze | H34: 45325 | I34: 148 | J34: 420 | K34: 0 | L34: Paid | M34: =Combined_Data!$I34*Combined_Data!$J34 -> 62160 | N34: =Combined_Data!$M34*(1-Combined_Data!$K34) -> 62160 | O34: =IF(Combined_Data!$N34>350000,"High",IF(Combined_Data!$N34>100000,"Medium","Low")) -> Low
A35: ORD-1034 | B35: PKG-004 | C35: DailyBrew Green Tea 25 bags | D35: Beverages | E35: West | F35: Convenience Store | G35: Emeka Okafor | H35: 45326 | I35: 337 | J35: 1200 | K35: 0.05 | L35: Paid | M35: =Combined_Data!$I35*Combined_Data!$J35 -> 404400 | N35: =Combined_Data!$M35*(1-Combined_Data!$K35) -> 384180 | O35: =IF(Combined_Data!$N35>350000,"High",IF(Combined_Data!$N35>100000,"Medium","Low")) -> High
A36: ORD-1035 | B36: PKG-005 | C36: HealthPure Bottled Water 500ml | D36: Beverages | E36: Central | F36: Pharmacy | G36: Fatima Musa | H36: 45327 | I36: 176 | J36: 200 | K36: 0 | L36: Pending | M36: =Combined_Data!$I36*Combined_Data!$J36 -> 35200 | N36: =Combined_Data!$M36*(1-Combined_Data!$K36) -> 35200 | O36: =IF(Combined_Data!$N36>350000,"High",IF(Combined_Data!$N36>100000,"Medium","Low")) -> Low
... A39: ORD-1038 | B39: PKG-008 | C39: NutriMix Cereal Box 500g | D39: Breakfast | E39: East | F39: Online | G39: Tunde Bello | H39: 45330 | I39: 147 | J39: 2800 | K39: 0 | L39: Paid | M39: =Combined_Data!$I39*Combined_Data!$J39 -> 411600 | N39: =Combined_Data!$M39*(1-Combined_Data!$K39) -> 411600 | O39: =IF(Combined_Data!$N39>350000,"High",IF(Combined_Data!$N39>100000,"Medium","Low")) -> High
A40: ORD-1039 | B40: PKG-009 | C40: CrispBite Corn Chips 100g | D40: Snacks | E40: West | F40: Convenience Store | G40: Ngozi Eze | H40: 45331 | I40: 63 | J40: 280 | K40: 0 | L40: Paid | M40: 17640 | N40: =Combined_Data!$M40*(1-Combined_Data!$K40) -> 17640 | O40: =IF(Combined_Data!$N40>350000,"High",IF(Combined_Data!$N40>100000,"Medium","Low")) -> Low
A41: ORD-1040 | B41: PKG-010 | C41: GoldenBite Chocolate Cookies 150g | D41: Baked Goods | E41: Central | F41: Pharmacy | G41: Emeka Okafor | H41: 45332 | I41: 458 | J41: 750 | K41: 0.05 | L41: Pending | M41: =Combined_Data!$I41*Combined_Data!$J41 -> 343500 | N41: =Combined_Data!$M41*(1-Combined_Data!$K41) -> 326325 | O41: =IF(Combined_Data!$N41>350000,"High",IF(Combined_Data!$N41>100000,"Medium","Low")) -> Medium
A42: ORD-1041 | B42: PKG-001 | C42: FreshSip Orange Juice 1L | D42: Beverages | E42: North | F42: Supermarket | G42: Fatima Musa | H42: 45333 | I42: 265 | J42: 990 | K42: 0 | L42: Paid | M42: =Combined_Data!$I42*Combined_Data!$J42 -> 262350 | N42: =Combined_Data!$M42*(1-Combined_Data!$K42) -> 262350 | O42: =IF(Combined_Data!$N42>350000,"High",IF(Combined_Data!$N42>100000,"Medium","Low")) -> Medium
A43: ORD-1042 | B43: PKG-002 | C43: NutriMix Granola Bar | D43: Snacks | E43: South | F43: Wholesaler | G43: Chidi Nwosu | H43: 45334 | I43: 478 | J43: 350 | K43: 0 | L43: Pending | M43: =Combined_Data!$I43*Combined_Data!$J43 -> 167300 | N43: =Combined_Data!$M43*(1-Combined_Data!$K43) -> 167300 | O43: =IF(Combined_Data!$N43>350000,"High",IF(Combined_Data!$N43>100000,"Medium","Low")) -> Medium
A44: ORD-1043 | B44: PKG-003 | C44: CrispBite Potato Chips 150g | D44: Snacks | E44: East | F44: Online | G44: Amara Osei | H44: 45335 | I44: 83 | J44: 420 | K44: 0.05 | L44: Paid | M44: =Combined_Data!$I44*Combined_Data!$J44 -> 34860 | N44: =Combined_Data!$M44*(1-Combined_Data!$K44) -> 33117 | O44: =IF(Combined_Data!$N44>350000,"High",IF(Combined_Data!$N44>100000,"Medium","Low")) -> Low
A45: ORD-1044 | B45: PKG-004 | C45: DailyBrew Green Tea 25 bags | D45: Beverages | E45: West | F45: Convenience Store | G45: Tunde Bello | H45: 45336 | I45: 297 | J45: 1200 | K45: 0 | L45: Paid | M45: =Combined_Data!$I45*Combined_Data!$J45 -> 356400 | N45: =Combined_Data!$M45*(1-Combined_Data!$K45) -> 356400 | O45: =IF(Combined_Data!$N45>350000,"High",IF(Combined_Data!$N45>100000,"Medium","Low")) -> High
A46: ORD-1045 | B46: PKG-005 | C46: HealthPure Bottled Water 500ml | D46: Beverages | E46: Central | F46: Pharmacy | G46: Ngozi Eze | H46: 45337 | I46: 392 | J46: 200 | K46: 0 | L46: Pending | M46: =Combined_Data!$I46*Combined_Data!$J46 -> 78400 | N46: =Combined_Data!$M46*(1-Combined_Data!$K46) -> 78400 | O46: =IF(Combined_Data!$N46>350000,"High",IF(Combined_Data!$N46>100000,"Medium","Low")) -> Low
A47: ORD-1046 | B47: PKG-006 | C47: GoldenBite Biscuits 200g | D47: Baked Goods | E47: North | F47: Supermarket | G47: Emeka Okafor | H47: 45338 | I47: 469 | J47: 895 | K47: 0.07 | L47: Paid | M47: =Combined_Data!$I47*Combined_Data!$J47 -> 419755 | N47: =Combined_Data!$M47*(1-Combined_Data!$K47) -> 390372.15 | O47: =IF(Combined_Data!$N47>350000,"High",IF(Combined_Data!$N47>100000,"Medium","Low")) -> High
A48: ORD-1047 | B48: PKG-007 | C48: FreshSip Mango Juice 500ml | D48: Beverages | E48: South | F48: Wholesaler | G48: Fatima Musa | H48: 45340 | I48: 80 | J48: 650 | K48: 0 | L48: Pending | M48: =Combined_Data!$I48*Combined_Data!$J48 -> 52000 | N48: =Combined_Data!$M48*(1-Combined_Data!$K48) -> 52000 | O48: =IF(Combined_Data!$N48>350000,"High",IF(Combined_Data!$N48>100000,"Medium","Low")) -> Low
A49: ORD-1048 | B49: PKG-008 | C49: NutriMix Cereal Box 500g | D49: Breakfast | E49: East | F49: Online | G49: Chidi Nwosu | H49: 45341 | I49: 56 | J49: 2800 | K49: 0 | L49: Paid | M49: =Combined_Data!$I49*Combined_Data!$J49 -> 156800 | N49: =Combined_Data!$M49*(1-Combined_Data!$K49) -> 156800 | O49: =IF(Combined_Data!$N49>350000,"High",IF(Combined_Data!$N49>100000,"Medium","Low")) -> Medium
A50: ORD-1049 | B50: PKG-009 | C50: CrispBite Corn Chips 100g | D50: Snacks | E50: West | F50: Convenience Store | G50: Amara Osei | H50: 45342 | I50: 450 | J50: 280 | K50: 0.1 | L50: Paid | M50: =Combined_Data!$I50*Combined_Data!$J50 -> 126000 | N50: =Combined_Data!$M50*(1-Combined_Data!$K50) -> 113400 | O50: =IF(Combined_Data!$N50>350000,"High",IF(Combined_Data!$N50>100000,"Medium","Low")) -> Medium
A51: ORD-1050 | B51: PKG-010 | C51: GoldenBite Chocolate Cookies 150g | D51: Baked Goods | E51: Central | F51: Pharmacy | G51: Tunde Bello | H51: 45343 | I51: 415 | J51: 750 | K51: 0 | L51: Pending | M51: =Combined_Data!$I51*Combined_Data!$J51 -> 311250 | N51: =Combined_Data!$M51*(1-Combined_Data!$K51) -> 311250 | O51: =IF(Combined_Data!$N51>350000,"High",IF(Combined_Data!$N51>100000,"Medium","Low")) -> Medium
A52: ORD-1051 | B52: PKG-001 | C52: FreshSip Orange Juice 1L | D52: Beverages | E52: North | F52: Supermarket | G52: Ngozi Eze | H52: 45344 | I52: 315 | J52: 990 | K52: 0 | L52: Paid | M52: =Combined_Data!$I52*Combined_Data!$J52 -> 311850 | N52: =Combined_Data!$M52*(1-Combined_Data!$K52) -> 311850 | O52: =IF(Combined_Data!$N52>350000,"High",IF(Combined_Data!$N52>100000,"Medium","Low")) -> Medium
... A56: ORD-1055 | B56: PKG-005 | C56: HealthPure Bottled Water 500ml | D56: Beverages | E56: Central | F56: Pharmacy | G56: Amara Osei | H56: 45348 | I56: 358 | J56: 200 | K56: 0.11 | L56: Pending | M56: =Combined_Data!$I56*Combined_Data!$J56 -> 71600 | N56: =Combined_Data!$M56*(1-Combined_Data!$K56) -> 63724 | O56: =IF(Combined_Data!$N56>350000,"High",IF(Combined_Data!$N56>100000,"Medium","Low")) -> Low
A57: ORD-1056 | B57: PKG-006 | C57: GoldenBite Biscuits 200g | D57: Baked Goods | E57: North | F57: Supermarket | G57: Tunde Bello | H57: 45349 | I57: 160 | J57: 895 | K57: 0 | L57: Paid | M57: 143200 | N57: =Combined_Data!$M57*(1-Combined_Data!$K57) -> 143200 | O57: =IF(Combined_Data!$N57>350000,"High",IF(Combined_Data!$N57>100000,"Medium","Low")) -> Medium
A58: ORD-1057 | B58: PKG-007 | C58: FreshSip Mango Juice 500ml | D58: Beverages | E58: South | F58: Wholesaler | G58: Ngozi Eze | H58: 45350 | I58: 403 | J58: 650 | K58: 0 | L58: Pending | M58: =Combined_Data!$I58*Combined_Data!$J58 -> 261950 | N58: =Combined_Data!$M58*(1-Combined_Data!$K58) -> 261950 | O58: =IF(Combined_Data!$N58>350000,"High",IF(Combined_Data!$N58>100000,"Medium","Low")) -> Medium
A59: ORD-1058 | B59: PKG-008 | C59: NutriMix Cereal Box 500g | D59: Breakfast | E59: East | F59: Online | G59: Emeka Okafor | H59: 45351 | I59: 67 | J59: 2800 | K59: 0.04 | L59: Paid | M59: =Combined_Data!$I59*Combined_Data!$J59 -> 187600 | N59: =Combined_Data!$M59*(1-Combined_Data!$K59) -> 180096 | O59: =IF(Combined_Data!$N59>350000,"High",IF(Combined_Data!$N59>100000,"Medium","Low")) -> Medium
A60: ORD-1059 | B60: PKG-009 | C60: CrispBite Corn Chips 100g | D60: Snacks | E60: West | F60: Convenience Store | G60: Fatima Musa | H60: 45352 | I60: 11 | J60: 280 | K60: 0 | L60: Paid | M60: =Combined_Data!$I60*Combined_Data!$J60 -> 3080 | N60: =Combined_Data!$M60*(1-Combined_Data!$K60) -> 3080 | O60: =IF(Combined_Data!$N60>350000,"High",IF(Combined_Data!$N60>100000,"Medium","Low")) -> Low
A61: ORD-1060 | B61: PKG-010 | C61: GoldenBite Chocolate Cookies 150g | D61: Baked Goods | E61: Central | F61: Pharmacy | G61: Chidi Nwosu | H61: 45353 | I61: 458 | J61: 750 | K61: 0 | L61: Pending | M61: =Combined_Data!$I61*Combined_Data!$J61 -> 343500 | N61: =Combined_Data!$M61*(1-Combined_Data!$K61) -> 343500 | O61: =IF(Combined_Data!$N61>350000,"High",IF(Combined_Data!$N61>100000,"Medium","Low")) -> Medium
A62: ORD-1061 | B62: PKG-001 | C62: FreshSip Orange Juice 1L | D62: Beverages | E62: North | F62: Supermarket | G62: Amara Osei | H62: 45354 | I62: 266 | J62: 990 | K62: 0.09 | L62: Paid | M62: =Combined_Data!$I62*Combined_Data!$J62 -> 263340 | N62: =Combined_Data!$M62*(1-Combined_Data!$K62) -> 239639.4 | O62: =IF(Combined_Data!$N62>350000,"High",IF(Combined_Data!$N62>100000,"Medium","Low")) -> Medium
A63: ORD-1062 | B63: PKG-002 | C63: NutriMix Granola Bar | D63: Snacks | E63: South | F63: Wholesaler | G63: Tunde Bello | H63: 45355 | I63: 64 | J63: 350 | K63: 0 | L63: Pending | M63: =Combined_Data!$I63*Combined_Data!$J63 -> 22400 | N63: =Combined_Data!$M63*(1-Combined_Data!$K63) -> 22400 | O63: =IF(Combined_Data!$N63>350000,"High",IF(Combined_Data!$N63>100000,"Medium","Low")) -> Low
A64: ORD-1063 | B64: PKG-003 | C64: CrispBite Potato Chips 150g | D64: Snacks | E64: East | F64: Online | G64: Ngozi Eze | H64: 45356 | I64: 162 | J64: 420 | K64: 0 | L64: Paid | M64: =Combined_Data!$I64*Combined_Data!$J64 -> 68040 | N64: =Combined_Data!$M64*(1-Combined_Data!$K64) -> 68040 | O64: =IF(Combined_Data!$N64>350000,"High",IF(Combined_Data!$N64>100000,"Medium","Low")) -> Low
A65: ORD-1064 | B65: PKG-004 | C65: DailyBrew Green Tea 25 bags | D65: Beverages | E65: West | F65: Convenience Store | G65: Emeka Okafor | H65: 45357 | I65: 269 | J65: 1200 | K65: 0.04 | L65: Paid | M65: =Combined_Data!$I65*Combined_Data!$J65 -> 322800 | N65: =Combined_Data!$M65*(1-Combined_Data!$K65) -> 309888 | O65: =IF(Combined_Data!$N65>350000,"High",IF(Combined_Data!$N65>100000,"Medium","Low")) -> Medium
A66: ORD-1065 | B66: PKG-005 | C66: HealthPure Bottled Water 500ml | D66: Beverages | E66: Central | F66: Pharmacy | G66: Fatima Musa | H66: 45358 | I66: 400 | J66: 200 | K66: 0 | L66: Pending | M66: =Combined_Data!$I66*Combined_Data!$J66 -> 80000 | N66: =Combined_Data!$M66*(1-Combined_Data!$K66) -> 80000 | O66: =IF(Combined_Data!$N66>350000,"High",IF(Combined_Data!$N66>100000,"Medium","Low")) -> Low
A67: ORD-1066 | B67: PKG-006 | C67: GoldenBite Biscuits 200g | D67: Baked Goods | E67: North | F67: Supermarket | G67: Chidi Nwosu | H67: 45359 | I67: 498 | J67: 895 | K67: 0 | L67: Paid | M67: =Combined_Data!$I67*Combined_Data!$J67 -> 445710 | N67: =Combined_Data!$M67*(1-Combined_Data!$K67) -> 445710 | O67: =IF(Combined_Data!$N67>350000,"High",IF(Combined_Data!$N67>100000,"Medium","Low")) -> High
A68: ORD-1067 | B68: PKG-007 | C68: FreshSip Mango Juice 500ml | D68: Beverages | E68: South | F68: Wholesaler | G68: Amara Osei | H68: 45360 | I68: 281 | J68: 650 | K68: 0.1 | L68: Pending | M68: =Combined_Data!$I68*Combined_Data!$J68 -> 182650 | N68: =Combined_Data!$M68*(1-Combined_Data!$K68) -> 164385 | O68: =IF(Combined_Data!$N68>350000,"High",IF(Combined_Data!$N68>100000,"Medium","Low")) -> Medium
A69: ORD-1068 | B69: PKG-008 | C69: NutriMix Cereal Box 500g | D69: Breakfast | E69: East | F69: Online | G69: Tunde Bello | H69: 45361 | I69: 260 | J69: 2800 | K69: 0 | L69: Paid | M69: =Combined_Data!$I69*Combined_Data!$J69 -> 728000 | N69: =Combined_Data!$M69*(1-Combined_Data!$K69) -> 728000 | O69: =IF(Combined_Data!$N69>350000,"High",IF(Combined_Data!$N69>100000,"Medium","Low")) -> High
... A72: ORD-1071 | B72: PKG-001 | C72: FreshSip Orange Juice 1L | D72: Beverages | E72: North | F72: Supermarket | G72: Fatima Musa | H72: 45364 | I72: 133 | J72: 990 | K72: 0 | L72: Paid | M72: =Combined_Data!$I72*Combined_Data!$J72 -> 131670 | N72: =Combined_Data!$M72*(1-Combined_Data!$K72) -> 131670 | O72: =IF(Combined_Data!$N72>350000,"High",IF(Combined_Data!$N72>100000,"Medium","Low")) -> Medium
A73: ORD-1072 | B73: PKG-002 | C73: NutriMix Granola Bar | D73: Snacks | E73: South | F73: Wholesaler | G73: Chidi Nwosu | H73: 45365 | I73: 89 | J73: 350 | K73: 0 | L73: Pending | M73: 31150 | N73: =Combined_Data!$M73*(1-Combined_Data!$K73) -> 31150 | O73: =IF(Combined_Data!$N73>350000,"High",IF(Combined_Data!$N73>100000,"Medium","Low")) -> Low
A74: ORD-1073 | B74: PKG-003 | C74: CrispBite Potato Chips 150g | D74: Snacks | E74: East | F74: Online | G74: Amara Osei | H74: 45366 | I74: 384 | J74: 420 | K74: 0.03 | L74: Paid | M74: =Combined_Data!$I74*Combined_Data!$J74 -> 161280 | N74: =Combined_Data!$M74*(1-Combined_Data!$K74) -> 156441.6 | O74: =IF(Combined_Data!$N74>350000,"High",IF(Combined_Data!$N74>100000,"Medium","Low")) -> Medium
A75: ORD-1074 | B75: PKG-004 | C75: DailyBrew Green Tea 25 bags | D75: Beverages | E75: West | F75: Convenience Store | G75: Tunde Bello | H75: 45367 | I75: 399 | J75: 1200 | K75: 0 | L75: Paid | M75: =Combined_Data!$I75*Combined_Data!$J75 -> 478800 | N75: =Combined_Data!$M75*(1-Combined_Data!$K75) -> 478800 | O75: =IF(Combined_Data!$N75>350000,"High",IF(Combined_Data!$N75>100000,"Medium","Low")) -> High
A76: ORD-1075 | B76: PKG-005 | C76: HealthPure Bottled Water 500ml | D76: Beverages | E76: Central | F76: Pharmacy | G76: Ngozi Eze | H76: 45368 | I76: 74 | J76: 200 | K76: 0 | L76: Pending | M76: =Combined_Data!$I76*Combined_Data!$J76 -> 14800 | N76: =Combined_Data!$M76*(1-Combined_Data!$K76) -> 14800 | O76: =IF(Combined_Data!$N76>350000,"High",IF(Combined_Data!$N76>100000,"Medium","Low")) -> Low
A77: ORD-1076 | B77: PKG-006 | C77: GoldenBite Biscuits 200g | D77: Baked Goods | E77: North | F77: Supermarket | G77: Emeka Okafor | H77: 45369 | I77: 253 | J77: 895 | K77: 0.04 | L77: Paid | M77: =Combined_Data!$I77*Combined_Data!$J77 -> 226435 | N77: =Combined_Data!$M77*(1-Combined_Data!$K77) -> 217377.6 | O77: =IF(Combined_Data!$N77>350000,"High",IF(Combined_Data!$N77>100000,"Medium","Low")) -> Medium
A78: ORD-1077 | B78: PKG-007 | C78: FreshSip Mango Juice 500ml | D78: Beverages | E78: South | F78: Wholesaler | G78: Fatima Musa | H78: 45370 | I78: 280 | J78: 650 | K78: 0 | L78: Pending | M78: =Combined_Data!$I78*Combined_Data!$J78 -> 182000 | N78: =Combined_Data!$M78*(1-Combined_Data!$K78) -> 182000 | O78: =IF(Combined_Data!$N78>350000,"High",IF(Combined_Data!$N78>100000,"Medium","Low")) -> Medium
A79: ORD-1078 | B79: PKG-008 | C79: NutriMix Cereal Box 500g | D79: Breakfast | E79: East | F79: Online | G79: Chidi Nwosu | H79: 45371 | I79: 226 | J79: 2800 | K79: 0 | L79: Paid | M79: =Combined_Data!$I79*Combined_Data!$J79 -> 632800 | N79: =Combined_Data!$M79*(1-Combined_Data!$K79) -> 632800 | O79: =IF(Combined_Data!$N79>350000,"High",IF(Combined_Data!$N79>100000,"Medium","Low")) -> High
A80: ORD-1079 | B80: PKG-009 | C80: CrispBite Corn Chips 100g | D80: Snacks | E80: West | F80: Convenience Store | G80: Amara Osei | H80: 45372 | I80: 485 | J80: 280 | K80: 0.11 | L80: Paid | M80: =Combined_Data!$I80*Combined_Data!$J80 -> 135800 | N80: =Combined_Data!$M80*(1-Combined_Data!$K80) -> 120862 | O80: =IF(Combined_Data!$N80>350000,"High",IF(Combined_Data!$N80>100000,"Medium","Low")) -> Medium
A81: ORD-1080 | B81: PKG-010 | C81: GoldenBite Chocolate Cookies 150g | D81: Baked Goods | E81: Central | F81: Pharmacy | G81: Tunde Bello | H81: 45373 | I81: 112 | J81: 750 | K81: 0 | L81: Pending | M81: =Combined_Data!$I81*Combined_Data!$J81 -> 84000 | N81: =Combined_Data!$M81*(1-Combined_Data!$K81) -> 84000 | O81: =IF(Combined_Data!$N81>350000,"High",IF(Combined_Data!$N81>100000,"Medium","Low")) -> Low
A82: ORD-1081 | B82: PKG-001 | C82: FreshSip Orange Juice 1L | D82: Beverages | E82: North | F82: Supermarket | G82: Ngozi Eze | H82: 45374 | I82: 214 | J82: 990 | K82: 0 | L82: Paid | M82: =Combined_Data!$I82*Combined_Data!$J82 -> 211860 | N82: =Combined_Data!$M82*(1-Combined_Data!$K82) -> 211860 | O82: =IF(Combined_Data!$N82>350000,"High",IF(Combined_Data!$N82>100000,"Medium","Low")) -> Medium
A83: ORD-1082 | B83: PKG-002 | C83: NutriMix Granola Bar | D83: Snacks | E83: South | F83: Wholesaler | G83: Emeka Okafor | H83: 45375 | I83: 342 | J83: 350 | K83: 0.14 | L83: Pending | M83: =Combined_Data!$I83*Combined_Data!$J83 -> 119700 | N83: =Combined_Data!$M83*(1-Combined_Data!$K83) -> 102942 | O83: =IF(Combined_Data!$N83>350000,"High",IF(Combined_Data!$N83>100000,"Medium","Low")) -> Medium
A84: ORD-1083 | B84: PKG-003 | C84: CrispBite Potato Chips 150g | D84: Snacks | E84: East | F84: Online | G84: Fatima Musa | H84: 45376 | I84: 241 | J84: 420 | K84: 0 | L84: Paid | M84: =Combined_Data!$I84*Combined_Data!$J84 -> 101220 | N84: =Combined_Data!$M84*(1-Combined_Data!$K84) -> 101220 | O84: =IF(Combined_Data!$N84>350000,"High",IF(Combined_Data!$N84>100000,"Medium","Low")) -> Medium
A85: ORD-1084 | B85: PKG-004 | C85: DailyBrew Green Tea 25 bags | D85: Beverages | E85: West | F85: Convenience Store | G85: Chidi Nwosu | H85: 45377 | I85: 125 | J85: 1200 | K85: 0 | L85: Paid | M85: =Combined_Data!$I85*Combined_Data!$J85 -> 150000 | N85: =Combined_Data!$M85*(1-Combined_Data!$K85) -> 150000 | O85: =IF(Combined_Data!$N85>350000,"High",IF(Combined_Data!$N85>100000,"Medium","Low")) -> Medium
... A90: ORD-1089 | B90: PKG-009 | C90: CrispBite Corn Chips 100g | D90: Snacks | E90: West | F90: Convenience Store | G90: Fatima Musa | H90: 45383 | I90: 179 | J90: 280 | K90: 0 | L90: Paid | M90: =Combined_Data!$I90*Combined_Data!$J90 -> 50120 | N90: =Combined_Data!$M90*(1-Combined_Data!$K90) -> 50120 | O90: =IF(Combined_Data!$N90>350000,"High",IF(Combined_Data!$N90>100000,"Medium","Low")) -> Low
A91: ORD-1090 | B91: PKG-010 | C91: GoldenBite Chocolate Cookies 150g | D91: Baked Goods | E91: Central | F91: Pharmacy | G91: Chidi Nwosu | H91: 45384 | I91: 111 | J91: 750 | K91: 0 | L91: Pending | M91: 83250 | N91: =Combined_Data!$M91*(1-Combined_Data!$K91) -> 83250 | O91: =IF(Combined_Data!$N91>350000,"High",IF(Combined_Data!$N91>100000,"Medium","Low")) -> Low
A92: ORD-1091 | B92: PKG-001 | C92: FreshSip Orange Juice 1L | D92: Beverages | E92: North | F92: Supermarket | G92: Amara Osei | H92: 45385 | I92: 258 | J92: 990 | K92: 0.04 | L92: Paid | M92: =Combined_Data!$I92*Combined_Data!$J92 -> 255420 | N92: =Combined_Data!$M92*(1-Combined_Data!$K92) -> 245203.2 | O92: =IF(Combined_Data!$N92>350000,"High",IF(Combined_Data!$N92>100000,"Medium","Low")) -> Medium
A93: ORD-1092 | B93: PKG-002 | C93: NutriMix Granola Bar | D93: Snacks | E93: South | F93: Wholesaler | G93: Tunde Bello | H93: 45386 | I93: 488 | J93: 350 | K93: 0 | L93: Pending | M93: =Combined_Data!$I93*Combined_Data!$J93 -> 170800 | N93: =Combined_Data!$M93*(1-Combined_Data!$K93) -> 170800 | O93: =IF(Combined_Data!$N93>350000,"High",IF(Combined_Data!$N93>100000,"Medium","Low")) -> Medium
A94: ORD-1093 | B94: PKG-003 | C94: CrispBite Potato Chips 150g | D94: Snacks | E94: East | F94: Online | G94: Ngozi Eze | H94: 45387 | I94: 305 | J94: 420 | K94: 0 | L94: Paid | M94: =Combined_Data!$I94*Combined_Data!$J94 -> 128100 | N94: =Combined_Data!$M94*(1-Combined_Data!$K94) -> 128100 | O94: =IF(Combined_Data!$N94>350000,"High",IF(Combined_Data!$N94>100000,"Medium","Low")) -> Medium
A95: ORD-1094 | B95: PKG-004 | C95: DailyBrew Green Tea 25 bags | D95: Beverages | E95: West | F95: Convenience Store | G95: Emeka Okafor | H95: 45388 | I95: 411 | J95: 1200 | K95: 0.07 | L95: Paid | M95: =Combined_Data!$I95*Combined_Data!$J95 -> 493200 | N95: =Combined_Data!$M95*(1-Combined_Data!$K95) -> 458676 | O95: =IF(Combined_Data!$N95>350000,"High",IF(Combined_Data!$N95>100000,"Medium","Low")) -> High
A96: ORD-1095 | B96: PKG-005 | C96: HealthPure Bottled Water 500ml | D96: Beverages | E96: Central | F96: Pharmacy | G96: Fatima Musa | H96: 45389 | I96: 58 | J96: 200 | K96: 0 | L96: Pending | M96: =Combined_Data!$I96*Combined_Data!$J96 -> 11600 | N96: =Combined_Data!$M96*(1-Combined_Data!$K96) -> 11600 | O96: =IF(Combined_Data!$N96>350000,"High",IF(Combined_Data!$N96>100000,"Medium","Low")) -> Low
A97: ORD-1096 | B97: PKG-006 | C97: GoldenBite Biscuits 200g | D97: Baked Goods | E97: North | F97: Supermarket | G97: Chidi Nwosu | H97: 45390 | I97: 230 | J97: 895 | K97: 0 | L97: Paid | M97: =Combined_Data!$I97*Combined_Data!$J97 -> 205850 | N97: =Combined_Data!$M97*(1-Combined_Data!$K97) -> 205850 | O97: =IF(Combined_Data!$N97>350000,"High",IF(Combined_Data!$N97>100000,"Medium","Low")) -> Medium
A98: ORD-1097 | B98: PKG-007 | C98: FreshSip Mango Juice 500ml | D98: Beverages | E98: South | F98: Wholesaler | G98: Amara Osei | H98: 45391 | I98: 220 | J98: 650 | K98: 0.11 | L98: Pending | M98: =Combined_Data!$I98*Combined_Data!$J98 -> 143000 | N98: =Combined_Data!$M98*(1-Combined_Data!$K98) -> 127270 | O98: =IF(Combined_Data!$N98>350000,"High",IF(Combined_Data!$N98>100000,"Medium","Low")) -> Medium
A99: ORD-1098 | B99: PKG-008 | C99: NutriMix Cereal Box 500g | D99: Breakfast | E99: East | F99: Online | G99: Tunde Bello | H99: 45392 | I99: 354 | J99: 2800 | K99: 0 | L99: Paid | M99: =Combined_Data!$I99*Combined_Data!$J99 -> 991200 | N99: =Combined_Data!$M99*(1-Combined_Data!$K99) -> 991200 | O99: =IF(Combined_Data!$N99>350000,"High",IF(Combined_Data!$N99>100000,"Medium","Low")) -> High
A100: ORD-1099 | B100: PKG-009 | C100: CrispBite Corn Chips 100g | D100: Snacks | E100: West | F100: Convenience Store | G100: Ngozi Eze | H100: 45393 | I100: 340 | J100: 280 | K100: 0 | L100: Paid | M100: =Combined_Data!$I100*Combined_Data!$J100 -> 95200 | N100: =Combined_Data!$M100*(1-Combined_Data!$K100) -> 95200 | O100: =IF(Combined_Data!$N100>350000,"High",IF(Combined_Data!$N100>100000,"Medium","Low")) -> Low
A101: ORD-1100 | B101: PKG-010 | C101: GoldenBite Chocolate Cookies 150g | D101: Baked Goods | E101: Central | F101: Pharmacy | G101: Emeka Okafor | H101: 45394 | I101: 216 | J101: 750 | K101: 0.12 | L101: Pending | M101: =Combined_Data!$I101*Combined_Data!$J101 -> 162000 | N101: =Combined_Data!$M101*(1-Combined_Data!$K101) -> 142560 | O101: =IF(Combined_Data!$N101>350000,"High",IF(Combined_Data!$N101>100000,"Medium","Low")) -> Medium
A102: ORD-1101 | B102: PKG-001 | C102: FreshSip Orange Juice 1L | D102: Beverages | E102: North | F102: Supermarket | G102: Fatima Musa | H102: 45395 | I102: 65 | J102: 990 | K102: 0 | L102: Paid | M102: =Combined_Data!$I102*Combined_Data!$J102 -> 64350 | N102: =Combined_Data!$M102*(1-Combined_Data!$K102) -> 64350 | O102: =IF(Combined_Data!$N102>350000,"High",IF(Combined_Data!$N102>100000,"Medium","Low")) -> Low
A103: ORD-1102 | B103: PKG-002 | C103: NutriMix Granola Bar | D103: Snacks | E103: South | F103: Wholesaler | G103: Chidi Nwosu | H103: 45396 | I103: 107 | J103: 350 | K103: 0 | L103: Pending | M103: =Combined_Data!$I103*Combined_Data!$J103 -> 37450 | N103: =Combined_Data!$M103*(1-Combined_Data!$K103) -> 37450 | O103: =IF(Combined_Data!$N103>350000,"High",IF(Combined_Data!$N103>100000,"Medium","Low")) -> Low
A104: ORD-1103 | B104: PKG-003 | C104: CrispBite Potato Chips 150g | D104: Snacks | E104: East | F104: Online | G104: Amara Osei | H104: 45397 | I104: 81 | J104: 420 | K104: 0.06 | L104: Paid | M104: =Combined_Data!$I104*Combined_Data!$J104 -> 34020 | N104: =Combined_Data!$M104*(1-Combined_Data!$K104) -> 31978.8 | O104: =IF(Combined_Data!$N104>350000,"High",IF(Combined_Data!$N104>100000,"Medium","Low")) -> Low
A105: ORD-1104 | B105: PKG-004 | C105: DailyBrew Green Tea 25 bags | D105: Beverages | E105: West | F105: Convenience Store | G105: Tunde Bello | H105: 45398 | I105: 100 | J105: 1200 | K105: 0 | L105: Paid | M105: 120000 | N105: =Combined_Data!$M105*(1-Combined_Data!$K105) -> 120000 | O105: =IF(Combined_Data!$N105>350000,"High",IF(Combined_Data!$N105>100000,"Medium","Low")) -> Medium
A106: ORD-1105 | B106: PKG-005 | C106: HealthPure Bottled Water 500ml | D106: Beverages | E106: Central | F106: Pharmacy | G106: Ngozi Eze | H106: 45399 | I106: 48 | J106: 200 | K106: 0 | L106: Pending | M106: =Combined_Data!$I106*Combined_Data!$J106 -> 9600 | N106: =Combined_Data!$M106*(1-Combined_Data!$K106) -> 9600 | O106: =IF(Combined_Data!$N106>350000,"High",IF(Combined_Data!$N106>100000,"Medium","Low")) -> Low
A107: ORD-1106 | B107: PKG-006 | C107: GoldenBite Biscuits 200g | D107: Baked Goods | E107: North | F107: Supermarket | G107: Emeka Okafor | H107: 45400 | I107: 451 | J107: 895 | K107: 0.03 | L107: Paid | M107: =Combined_Data!$I107*Combined_Data!$J107 -> 403645 | N107: =Combined_Data!$M107*(1-Combined_Data!$K107) -> 391535.65 | O107: =IF(Combined_Data!$N107>350000,"High",IF(Combined_Data!$N107>100000,"Medium","Low")) -> High
A108: ORD-1107 | B108: PKG-007 | C108: FreshSip Mango Juice 500ml | D108: Beverages | E108: South | F108: Wholesaler | G108: Fatima Musa | H108: 45401 | I108: 343 | J108: 650 | K108: 0 | L108: Pending | M108: =Combined_Data!$I108*Combined_Data!$J108 -> 222950 | N108: =Combined_Data!$M108*(1-Combined_Data!$K108) -> 222950 | O108: =IF(Combined_Data!$N108>350000,"High",IF(Combined_Data!$N108>100000,"Medium","Low")) -> Medium
A109: ORD-1108 | B109: PKG-008 | C109: NutriMix Cereal Box 500g | D109: Breakfast | E109: East | F109: Online | G109: Chidi Nwosu | H109: 45402 | I109: 438 | J109: 2800 | K109: 0 | L109: Paid | M109: =Combined_Data!$I109*Combined_Data!$J109 -> 1226400 | N109: =Combined_Data!$M109*(1-Combined_Data!$K109) -> 1226400 | O109: =IF(Combined_Data!$N109>350000,"High",IF(Combined_Data!$N109>100000,"Medium","Low")) -> High
A110: ORD-1109 | B110: PKG-009 | C110: CrispBite Corn Chips 100g | D110: Snacks | E110: West | F110: Convenience Store | G110: Amara Osei | H110: 45403 | I110: 57 | J110: 280 | K110: 0.13 | L110: Paid | M110: =Combined_Data!$I110*Combined_Data!$J110 -> 15960 | N110: =Combined_Data!$M110*(1-Combined_Data!$K110) -> 13885.2 | O110: =IF(Combined_Data!$N110>350000,"High",IF(Combined_Data!$N110>100000,"Medium","Low")) -> Low
A111: ORD-1110 | B111: PKG-010 | C111: GoldenBite Chocolate Cookies 150g | D111: Baked Goods | E111: Central | F111: Pharmacy | G111: Tunde Bello | H111: 45404 | I111: 95 | J111: 750 | K111: 0 | L111: Pending | M111: =Combined_Data!$I111*Combined_Data!$J111 -> 71250 | N111: =Combined_Data!$M111*(1-Combined_Data!$K111) -> 71250 | O111: =IF(Combined_Data!$N111>350000,"High",IF(Combined_Data!$N111>100000,"Medium","Low")) -> Low
A112: ORD-1111 | B112: PKG-001 | C112: FreshSip Orange Juice 1L | D112: Beverages | E112: North | F112: Supermarket | G112: Ngozi Eze | H112: 45405 | I112: 256 | J112: 990 | K112: 0 | L112: Paid | M112: =Combined_Data!$I112*Combined_Data!$J112 -> 253440 | N112: =Combined_Data!$M112*(1-Combined_Data!$K112) -> 253440 | O112: =IF(Combined_Data!$N112>350000,"High",IF(Combined_Data!$N112>100000,"Medium","Low")) -> Medium
A113: ORD-1112 | B113: PKG-002 | C113: NutriMix Granola Bar | D113: Snacks | E113: South | F113: Wholesaler | G113: Emeka Okafor | H113: 45406 | I113: 215 | J113: 350 | K113: 0.04 | L113: Pending | M113: =Combined_Data!$I113*Combined_Data!$J113 -> 75250 | N113: =Combined_Data!$M113*(1-Combined_Data!$K113) -> 72240 | O113: =IF(Combined_Data!$N113>350000,"High",IF(Combined_Data!$N113>100000,"Medium","Low")) -> Low
A114: ORD-1113 | B114: PKG-003 | C114: CrispBite Potato Chips 150g | D114: Snacks | E114: East | F114: Online | G114: Fatima Musa | H114: 45407 | I114: 160 | J114: 420 | K114: 0 | L114: Paid | M114: 67200 | N114: =Combined_Data!$M114*(1-Combined_Data!$K114) -> 67200 | O114: =IF(Combined_Data!$N114>350000,"High",IF(Combined_Data!$N114>100000,"Medium","Low")) -> Low
...

Sheet Pivot Tables
C5: 1. Monthly revenue across all three years | J5: 3. Which product category contributes the most to total revenue — and which contributes the least? | Q5: 5. Which sales channel generates the highest total paid revenue — and which is the weakest performer?
C7: Payment Status | D7: Paid | J7: Payment Status | K7: Paid | Q7: Payment Status | R7: Paid
C9: Sum of Net Revenue (₦) | D9: Column Labels | J9: Row Labels | K9: Sum of Net Revenue (₦) | Q9: Row Labels | R9: Sum of Net Revenue (₦)
C10: Row Labels | D10: 2024 | E10: 2025 | F10: 2026 | G10: Grand Total | J10: Baked Goods | K10: 25889411 | Q10: Online | R10: 28690898
C11: Jan | D11: 5108949.5 | E11: 4766789.5 | F11: 5244011.8 | G11: 15119751 | J11: Beverages | K11: 41917738 | Q11: Supermarket | R11: 25782802
C12: Feb | D12: 4080558.6 | E12: 5661650.4 | F12: 5333289 | G12: 15075498 | J12: Breakfast | K12: 31746372 | Q12: Convenience Store | R12: 22826856
C13: Mar | D13: 4918146.6 | E13: 5851903.3 | F13: 5829287.8 | G13: 16599338 | J13: Snacks | K13: 20595780 | Q13: Wholesaler | R13: 22530255
C14: Apr | D14: 5978014.8 | E14: 4488471.2 | F14: 5604900.2 | G14: 16071386 | J14: Grand Total | K14: 1.201493e+08 | Q14: Pharmacy | R14: 20318491
C15: May | D15: 33880 | E15: 2758113.4 | F15: 2959197.8 | G15: 5751191.2 | Q15: Grand Total | R15: 1.201493e+08
C16: Jun | D16: 4224813.8 | E16: 6315554.6 | G16: 10540368
C17: Jul | D17: 4074311.8 | E17: 5084961.1 | G17: 9159272.9
C18: Aug | D18: 3302361 | E18: 4220503.1 | G18: 7522864.1
C19: Sep | D19: 2903069.3 | E19: 4278758.1 | G19: 7181827.4
C20: Oct | D20: 3353023.2 | E20: 4379108.2 | G20: 7732131.4
C21: Nov | D21: 2909902.6 | E21: 4129634.8 | G21: 7039537.4
C22: Dec | D22: 996842.5 | E22: 1359293.1 | G22: 2356135.6
C23: Grand Total | D23: 41883874 | E23: 53294741 | F23: 24970687 | G23: 1.201493e+08
J25: 4. Which five products are driving the most revenue for NouraMart | Q25: 6. How do we compare sales rep performance side by side using a pivot table?
C27: 2. Total paid revenue per region | J27: Payment Status | K27: Paid | Q27: Payment Status | R27: Paid
C29: Payment Status | D29: Paid | J29: Row Labels | K29: Sum of Net Revenue (₦) | Q29: Row Labels | R29: Sum of Net Revenue (₦)
J30: NutriMix Cereal Box 500g | K30: 31746372 | Q30: Amara Osei | R30: 16630815
C31: Row Labels | D31: Sum of Net Revenue (₦) | J31: DailyBrew Green Tea 25 bags | K31: 16727004 | Q31: Chidi Nwosu | R31: 19592694
C32: East | D32: 30799215 | J32: GoldenBite Biscuits 200g | K32: 13868401 | Q32: Emeka Okafor | R32: 18952286
C33: North | D33: 26072316 | J33: FreshSip Orange Juice 1L | K33: 11949013 | Q33: Fatima Musa | R33: 17690430
C34: West | D34: 24112143 | J34: GoldenBite Chocolate Cookies 150g | K34: 8343457.5 | Q34: Ngozi Eze | R34: 18976359
C35: Central | D35: 20957379 | J35: Grand Total | K35: 82634247 | Q35: Tunde Bello | R35: 28306718
C36: South | D36: 18208248 | Q36: Grand Total | R36: 1.201493e+08
C37: Grand Total | D37: 1.201493e+08
J38: Row Labels | K38: Sum of Net Revenue (₦) | L38: Remainder
J39: GoldenBite Chocolate Cookies 150g | K39: 8343457.5 | L39: =31746372-K39 -> 23402914
J40: FreshSip Orange Juice 1L | K40: 11949013 | L40: =31746372-K40 -> 19797359
J41: GoldenBite Biscuits 200g | K41: 13868401 | L41: =31746372-K41 -> 17877971
J42: DailyBrew Green Tea 25 bags | K42: 16727004 | L42: =31746372-K42 -> 15019368
J43: NutriMix Cereal Box 500g | K43: 31746372 | L43: =31746372-K43 -> 0
J44: Grand Total | K44: 82634247

Sheet KPIs
A1: KPI | B1: Answer
A2: Total Net Revenue | B2: =SUMIF(data[Payment Status], "Paid", data[Net Revenue (₦)]) -> 1.201493e+08
A3: Total Orders | B3: =COUNTIF(data[Payment Status], "Paid") -> 910
A4: Average Order Value | B4: =AVERAGEIF(data[Payment Status],"Paid",data[Net Revenue (₦)]) -> 132032.2
A5: Top Region | B5: =INDEX(data[Region],MATCH(_xlfn.MAXIFS(data[Net Revenue (₦)],data[Payment Status],"Paid"),data[Net Revenue (₦)],0)) -> East
A6: Top Product | B6: =INDEX(data[Product Name],MATCH(_xlfn.MAXIFS(data[Net Revenue (₦)],data[Payment Status],"Paid"),data[Net Revenue (₦)],0)) -> NutriMix Cereal Box 500g

Sheet Dashboard
